[
  {
    "id":0,
    "title":"Acer Nitro 5 AN515 57 51G6",
    "alias":"acer-nitro-5-an515-57-51g6",
    "rating":4.806502153672118,
    "content":"Lorem ipsum dolor sit amet, consectetuer adipiscing elit. Aenean commodo ligula eget dolor. Aenean massa. Cum sociis natoque penatibus et magnis dis parturient montes, nascetur ridiculus mus. Donec quam felis, ultricies nec, pellentesque eu, pretium quis, sem. Nulla consequat massa quis enim. Donec pede justo, fringilla vel, aliquet nec, vulputate eget, arcu. In enim justo, rhoncus ut, imperdiet a, venenatis vitae, justo. Nullam dictum felis eu pede mollis pretium. Integer tincidunt. Cras dapibus. Vivamus elementum semper nisi. Aenean vulputate eleifend tellus. Aenean leo ligula, porttitor eu, consequat vitae, eleifend ac, enim. Aliquam lorem ante, dapibus in, viverra quis, feugiat a, tellus. Phasellus viverra nulla ut metus varius laoreet. Quisque rutrum. Aenean imperdiet. Etiam ultricies nisi vel augue. Curabitur ullamcorper ultricies nisi. Nam eget dui. Etiam rhoncus. Maecenas tempus, tellus eget condimentum rhoncus, sem quam semper libero, sit amet adipiscing sem neque sed ipsum. Nam quam nunc, blandit vel, luctus pulvinar, hendrerit id, lorem. Maecenas nec odio et ante tincidunt tempus. Donec vitae sapien ut libero venenatis faucibus. Nullam quis ante. Etiam sit amet orci eget eros faucibus tincidunt. Duis leo. Sed fringilla mauris sit amet nibh. Donec sodales sagittis magna. Sed consequat, leo eget bibendum sodales, augue velit cursus nunc,",
    "versions":[
      {
        "id":0,
        "title":"3GB-32GB",
        "alias":"3gb-32gb",
        "image":"/upload/Acer Nitro 5 AN515 57 51G6.png" ,
        "price":319.49
      },{
        "id":1,
        "title":"4GB-64GB",
        "alias":"4gb-64gb",
        "image":"/upload/Acer Nitro 5 AN515 57 51G6.png" ,
        "price":383.39
      }
    ],
      "albums":[
        {
          "image":"/upload/Acer Nitro 5 AN515 57 51G6.png"
        },
        {
          "image":"/upload/Acer Nitro 5 AN515 57 51G6.png"
        },
        {
          "image":"/upload/Acer Nitro 5 AN515 57 51G6.png"
        },
        {
          "image":"/upload/Acer Nitro 5 AN515 57 51G6.png"
        },
        {
          "image":"/upload/Acer Nitro 5 AN515 57 51G6.png"
        }
      ]
  }
,{
    "id":1,
    "title":"Acer Nitro 5 Gaming AN515",
    "alias":"acer-nitro-5-gaming-an515",
    "rating":1.0879293148947533,
    "content":"Lorem ipsum dolor sit amet, consectetuer adipiscing elit. Aenean commodo ligula eget dolor. Aenean massa. Cum sociis natoque penatibus et magnis dis parturient montes, nascetur ridiculus mus. Donec quam felis, ultricies nec, pellentesque eu, pretium quis, sem. Nulla consequat massa quis enim. Donec pede justo, fringilla vel, aliquet nec, vulputate eget, arcu. In enim justo, rhoncus ut, imperdiet a, venenatis vitae, justo. Nullam dictum felis eu pede mollis pretium. Integer tincidunt. Cras dapibus. Vivamus elementum semper nisi. Aenean vulputate eleifend tellus. Aenean leo ligula, porttitor eu, consequat vitae, eleifend ac, enim. Aliquam lorem ante, dapibus in, viverra quis, feugiat a, tellus. Phasellus viverra nulla ut metus varius laoreet. Quisque rutrum. Aenean imperdiet. Etiam ultricies nisi vel augue. Curabitur ullamcorper ultricies nisi. Nam eget dui. Etiam rhoncus. Maecenas tempus, tellus eget condimentum rhoncus, sem quam semper libero, sit amet adipiscing sem neque sed ipsum. Nam quam nunc, blandit vel, luctus pulvinar, hendrerit id, lorem. Maecenas nec odio et ante tincidunt tempus. Donec vitae sapien ut libero venenatis faucibus. Nullam quis ante. Etiam sit amet orci eget eros faucibus tincidunt. Duis leo. Sed fringilla mauris sit amet nibh. Donec sodales sagittis magna. Sed consequat, leo eget bibendum sodales, augue velit cursus nunc,",
    "versions":[
      {
        "id":0,
        "title":"3GB-32GB",
        "alias":"3gb-32gb",
        "image":"/upload/Acer Nitro 5 Gaming AN515.png" ,
        "price":285.52
      },{
        "id":1,
        "title":"4GB-64GB",
        "alias":"4gb-64gb",
        "image":"/upload/Acer Nitro 5 Gaming AN515.png" ,
        "price":342.62
      }
    ],
      "albums":[
        {
          "image":"/upload/Acer Nitro 5 Gaming AN515.png"
        },
        {
          "image":"/upload/Acer Nitro 5 Gaming AN515.png"
        },
        {
          "image":"/upload/Acer Nitro 5 Gaming AN515.png"
        },
        {
          "image":"/upload/Acer Nitro 5 Gaming AN515.png"
        },
        {
          "image":"/upload/Acer Nitro 5 Gaming AN515.png"
        }
      ]
  }
,{
    "id":2,
    "title":"Asus ROG Phone 3",
    "alias":"asus-rog-phone-3",
    "rating":2.7525586993681364,
    "content":"Lorem ipsum dolor sit amet, consectetuer adipiscing elit. Aenean commodo ligula eget dolor. Aenean massa. Cum sociis natoque penatibus et magnis dis parturient montes, nascetur ridiculus mus. Donec quam felis, ultricies nec, pellentesque eu, pretium quis, sem. Nulla consequat massa quis enim. Donec pede justo, fringilla vel, aliquet nec, vulputate eget, arcu. In enim justo, rhoncus ut, imperdiet a, venenatis vitae, justo. Nullam dictum felis eu pede mollis pretium. Integer tincidunt. Cras dapibus. Vivamus elementum semper nisi. Aenean vulputate eleifend tellus. Aenean leo ligula, porttitor eu, consequat vitae, eleifend ac, enim. Aliquam lorem ante, dapibus in, viverra quis, feugiat a, tellus. Phasellus viverra nulla ut metus varius laoreet. Quisque rutrum. Aenean imperdiet. Etiam ultricies nisi vel augue. Curabitur ullamcorper ultricies nisi. Nam eget dui. Etiam rhoncus. Maecenas tempus, tellus eget condimentum rhoncus, sem quam semper libero, sit amet adipiscing sem neque sed ipsum. Nam quam nunc, blandit vel, luctus pulvinar, hendrerit id, lorem. Maecenas nec odio et ante tincidunt tempus. Donec vitae sapien ut libero venenatis faucibus. Nullam quis ante. Etiam sit amet orci eget eros faucibus tincidunt. Duis leo. Sed fringilla mauris sit amet nibh. Donec sodales sagittis magna. Sed consequat, leo eget bibendum sodales, augue velit cursus nunc,",
    "versions":[
      {
        "id":0,
        "title":"3GB-32GB",
        "alias":"3gb-32gb",
        "image":"/upload/Asus ROG Phone 3.png" ,
        "price":80.82
      },{
        "id":1,
        "title":"4GB-64GB",
        "alias":"4gb-64gb",
        "image":"/upload/Asus ROG Phone 3.png" ,
        "price":96.98 ,
        "salePrice":22.34
      }
    ],
      "albums":[
        {
          "image":"/upload/Asus ROG Phone 3.png"
        },
        {
          "image":"/upload/Asus ROG Phone 3.png"
        },
        {
          "image":"/upload/Asus ROG Phone 3.png"
        },
        {
          "image":"/upload/Asus ROG Phone 3.png"
        },
        {
          "image":"/upload/Asus ROG Phone 3.png"
        }
      ]
  }
,{
    "id":3,
    "title":"Asus ROG Phone 5",
    "alias":"asus-rog-phone-5",
    "rating":2.1004842702215623,
    "content":"Lorem ipsum dolor sit amet, consectetuer adipiscing elit. Aenean commodo ligula eget dolor. Aenean massa. Cum sociis natoque penatibus et magnis dis parturient montes, nascetur ridiculus mus. Donec quam felis, ultricies nec, pellentesque eu, pretium quis, sem. Nulla consequat massa quis enim. Donec pede justo, fringilla vel, aliquet nec, vulputate eget, arcu. In enim justo, rhoncus ut, imperdiet a, venenatis vitae, justo. Nullam dictum felis eu pede mollis pretium. Integer tincidunt. Cras dapibus. Vivamus elementum semper nisi. Aenean vulputate eleifend tellus. Aenean leo ligula, porttitor eu, consequat vitae, eleifend ac, enim. Aliquam lorem ante, dapibus in, viverra quis, feugiat a, tellus. Phasellus viverra nulla ut metus varius laoreet. Quisque rutrum. Aenean imperdiet. Etiam ultricies nisi vel augue. Curabitur ullamcorper ultricies nisi. Nam eget dui. Etiam rhoncus. Maecenas tempus, tellus eget condimentum rhoncus, sem quam semper libero, sit amet adipiscing sem neque sed ipsum. Nam quam nunc, blandit vel, luctus pulvinar, hendrerit id, lorem. Maecenas nec odio et ante tincidunt tempus. Donec vitae sapien ut libero venenatis faucibus. Nullam quis ante. Etiam sit amet orci eget eros faucibus tincidunt. Duis leo. Sed fringilla mauris sit amet nibh. Donec sodales sagittis magna. Sed consequat, leo eget bibendum sodales, augue velit cursus nunc,",
    "versions":[
      {
        "id":0,
        "title":"3GB-32GB",
        "alias":"3gb-32gb",
        "image":"/upload/Asus ROG Phone 5.png" ,
        "price":156.58
      },{
        "id":1,
        "title":"4GB-64GB",
        "alias":"4gb-64gb",
        "image":"/upload/Asus ROG Phone 5.png" ,
        "price":187.90
      }
    ],
      "albums":[
        {
          "image":"/upload/Asus ROG Phone 5.png"
        },
        {
          "image":"/upload/Asus ROG Phone 5.png"
        },
        {
          "image":"/upload/Asus ROG Phone 5.png"
        },
        {
          "image":"/upload/Asus ROG Phone 5.png"
        },
        {
          "image":"/upload/Asus ROG Phone 5.png"
        }
      ]
  }
,{
    "id":4,
    "title":"Asus TUF Gaming FX706HE",
    "alias":"asus-tuf-gaming-fx706he",
    "rating":3.9415983562886794,
    "content":"Lorem ipsum dolor sit amet, consectetuer adipiscing elit. Aenean commodo ligula eget dolor. Aenean massa. Cum sociis natoque penatibus et magnis dis parturient montes, nascetur ridiculus mus. Donec quam felis, ultricies nec, pellentesque eu, pretium quis, sem. Nulla consequat massa quis enim. Donec pede justo, fringilla vel, aliquet nec, vulputate eget, arcu. In enim justo, rhoncus ut, imperdiet a, venenatis vitae, justo. Nullam dictum felis eu pede mollis pretium. Integer tincidunt. Cras dapibus. Vivamus elementum semper nisi. Aenean vulputate eleifend tellus. Aenean leo ligula, porttitor eu, consequat vitae, eleifend ac, enim. Aliquam lorem ante, dapibus in, viverra quis, feugiat a, tellus. Phasellus viverra nulla ut metus varius laoreet. Quisque rutrum. Aenean imperdiet. Etiam ultricies nisi vel augue. Curabitur ullamcorper ultricies nisi. Nam eget dui. Etiam rhoncus. Maecenas tempus, tellus eget condimentum rhoncus, sem quam semper libero, sit amet adipiscing sem neque sed ipsum. Nam quam nunc, blandit vel, luctus pulvinar, hendrerit id, lorem. Maecenas nec odio et ante tincidunt tempus. Donec vitae sapien ut libero venenatis faucibus. Nullam quis ante. Etiam sit amet orci eget eros faucibus tincidunt. Duis leo. Sed fringilla mauris sit amet nibh. Donec sodales sagittis magna. Sed consequat, leo eget bibendum sodales, augue velit cursus nunc,",
    "versions":[
      {
        "id":0,
        "title":"3GB-32GB",
        "alias":"3gb-32gb",
        "image":"/upload/Asus TUF Gaming FX706HE.png" ,
        "price":343.55 ,
        "salePrice":93.34
      },{
        "id":1,
        "title":"4GB-64GB",
        "alias":"4gb-64gb",
        "image":"/upload/Asus TUF Gaming FX706HE.png" ,
        "price":412.26 ,
        "salePrice":100.66
      }
    ],
      "albums":[
        {
          "image":"/upload/Asus TUF Gaming FX706HE.png"
        },
        {
          "image":"/upload/Asus TUF Gaming FX706HE.png"
        },
        {
          "image":"/upload/Asus TUF Gaming FX706HE.png"
        },
        {
          "image":"/upload/Asus TUF Gaming FX706HE.png"
        },
        {
          "image":"/upload/Asus TUF Gaming FX706HE.png"
        }
      ]
  }
,{
    "id":5,
    "title":"Asus VivoBook A515EA",
    "alias":"asus-vivobook-a515ea",
    "rating":2.4723351132319635,
    "content":"Lorem ipsum dolor sit amet, consectetuer adipiscing elit. Aenean commodo ligula eget dolor. Aenean massa. Cum sociis natoque penatibus et magnis dis parturient montes, nascetur ridiculus mus. Donec quam felis, ultricies nec, pellentesque eu, pretium quis, sem. Nulla consequat massa quis enim. Donec pede justo, fringilla vel, aliquet nec, vulputate eget, arcu. In enim justo, rhoncus ut, imperdiet a, venenatis vitae, justo. Nullam dictum felis eu pede mollis pretium. Integer tincidunt. Cras dapibus. Vivamus elementum semper nisi. Aenean vulputate eleifend tellus. Aenean leo ligula, porttitor eu, consequat vitae, eleifend ac, enim. Aliquam lorem ante, dapibus in, viverra quis, feugiat a, tellus. Phasellus viverra nulla ut metus varius laoreet. Quisque rutrum. Aenean imperdiet. Etiam ultricies nisi vel augue. Curabitur ullamcorper ultricies nisi. Nam eget dui. Etiam rhoncus. Maecenas tempus, tellus eget condimentum rhoncus, sem quam semper libero, sit amet adipiscing sem neque sed ipsum. Nam quam nunc, blandit vel, luctus pulvinar, hendrerit id, lorem. Maecenas nec odio et ante tincidunt tempus. Donec vitae sapien ut libero venenatis faucibus. Nullam quis ante. Etiam sit amet orci eget eros faucibus tincidunt. Duis leo. Sed fringilla mauris sit amet nibh. Donec sodales sagittis magna. Sed consequat, leo eget bibendum sodales, augue velit cursus nunc,",
    "versions":[
      {
        "id":0,
        "title":"3GB-32GB",
        "alias":"3gb-32gb",
        "image":"/upload/Asus VivoBook A515EA.png" ,
        "price":254.89
      },{
        "id":1,
        "title":"4GB-64GB",
        "alias":"4gb-64gb",
        "image":"/upload/Asus VivoBook A515EA.png" ,
        "price":305.87
      }
    ],
      "albums":[
        {
          "image":"/upload/Asus VivoBook A515EA.png"
        },
        {
          "image":"/upload/Asus VivoBook A515EA.png"
        },
        {
          "image":"/upload/Asus VivoBook A515EA.png"
        },
        {
          "image":"/upload/Asus VivoBook A515EA.png"
        },
        {
          "image":"/upload/Asus VivoBook A515EA.png"
        }
      ]
  }
,{
    "id":6,
    "title":"Dell Gaming G15",
    "alias":"dell-gaming-g15",
    "rating":2.6926061060717976,
    "content":"Lorem ipsum dolor sit amet, consectetuer adipiscing elit. Aenean commodo ligula eget dolor. Aenean massa. Cum sociis natoque penatibus et magnis dis parturient montes, nascetur ridiculus mus. Donec quam felis, ultricies nec, pellentesque eu, pretium quis, sem. Nulla consequat massa quis enim. Donec pede justo, fringilla vel, aliquet nec, vulputate eget, arcu. In enim justo, rhoncus ut, imperdiet a, venenatis vitae, justo. Nullam dictum felis eu pede mollis pretium. Integer tincidunt. Cras dapibus. Vivamus elementum semper nisi. Aenean vulputate eleifend tellus. Aenean leo ligula, porttitor eu, consequat vitae, eleifend ac, enim. Aliquam lorem ante, dapibus in, viverra quis, feugiat a, tellus. Phasellus viverra nulla ut metus varius laoreet. Quisque rutrum. Aenean imperdiet. Etiam ultricies nisi vel augue. Curabitur ullamcorper ultricies nisi. Nam eget dui. Etiam rhoncus. Maecenas tempus, tellus eget condimentum rhoncus, sem quam semper libero, sit amet adipiscing sem neque sed ipsum. Nam quam nunc, blandit vel, luctus pulvinar, hendrerit id, lorem. Maecenas nec odio et ante tincidunt tempus. Donec vitae sapien ut libero venenatis faucibus. Nullam quis ante. Etiam sit amet orci eget eros faucibus tincidunt. Duis leo. Sed fringilla mauris sit amet nibh. Donec sodales sagittis magna. Sed consequat, leo eget bibendum sodales, augue velit cursus nunc,",
    "versions":[
      {
        "id":0,
        "title":"3GB-32GB",
        "alias":"3gb-32gb",
        "image":"/upload/Dell Gaming G15.png"
      },{
        "id":1,
        "title":"4GB-64GB",
        "alias":"4gb-64gb",
        "image":"/upload/Dell Gaming G15.png"
      }
    ],
      "albums":[
        {
          "image":"/upload/Dell Gaming G15.png"
        },
        {
          "image":"/upload/Dell Gaming G15.png"
        },
        {
          "image":"/upload/Dell Gaming G15.png"
        },
        {
          "image":"/upload/Dell Gaming G15.png"
        },
        {
          "image":"/upload/Dell Gaming G15.png"
        }
      ]
  }
,{
    "id":7,
    "title":"Dell Inspiron 15 3511",
    "alias":"dell-inspiron-15-3511",
    "rating":4.409107253589442,
    "content":"Lorem ipsum dolor sit amet, consectetuer adipiscing elit. Aenean commodo ligula eget dolor. Aenean massa. Cum sociis natoque penatibus et magnis dis parturient montes, nascetur ridiculus mus. Donec quam felis, ultricies nec, pellentesque eu, pretium quis, sem. Nulla consequat massa quis enim. Donec pede justo, fringilla vel, aliquet nec, vulputate eget, arcu. In enim justo, rhoncus ut, imperdiet a, venenatis vitae, justo. Nullam dictum felis eu pede mollis pretium. Integer tincidunt. Cras dapibus. Vivamus elementum semper nisi. Aenean vulputate eleifend tellus. Aenean leo ligula, porttitor eu, consequat vitae, eleifend ac, enim. Aliquam lorem ante, dapibus in, viverra quis, feugiat a, tellus. Phasellus viverra nulla ut metus varius laoreet. Quisque rutrum. Aenean imperdiet. Etiam ultricies nisi vel augue. Curabitur ullamcorper ultricies nisi. Nam eget dui. Etiam rhoncus. Maecenas tempus, tellus eget condimentum rhoncus, sem quam semper libero, sit amet adipiscing sem neque sed ipsum. Nam quam nunc, blandit vel, luctus pulvinar, hendrerit id, lorem. Maecenas nec odio et ante tincidunt tempus. Donec vitae sapien ut libero venenatis faucibus. Nullam quis ante. Etiam sit amet orci eget eros faucibus tincidunt. Duis leo. Sed fringilla mauris sit amet nibh. Donec sodales sagittis magna. Sed consequat, leo eget bibendum sodales, augue velit cursus nunc,",
    "versions":[
      {
        "id":0,
        "title":"3GB-32GB",
        "alias":"3gb-32gb",
        "image":"/upload/Dell Inspiron 15 3511.png" ,
        "price":385.25
      },{
        "id":1,
        "title":"4GB-64GB",
        "alias":"4gb-64gb",
        "image":"/upload/Dell Inspiron 15 3511.png" ,
        "price":462.30 ,
        "salePrice":217.25
      }
    ],
      "albums":[
        {
          "image":"/upload/Dell Inspiron 15 3511.png"
        },
        {
          "image":"/upload/Dell Inspiron 15 3511.png"
        },
        {
          "image":"/upload/Dell Inspiron 15 3511.png"
        },
        {
          "image":"/upload/Dell Inspiron 15 3511.png"
        },
        {
          "image":"/upload/Dell Inspiron 15 3511.png"
        }
      ]
  }
,{
    "id":8,
    "title":"Dell Vostro 3400",
    "alias":"dell-vostro-3400",
    "rating":2.487612280492267,
    "content":"Lorem ipsum dolor sit amet, consectetuer adipiscing elit. Aenean commodo ligula eget dolor. Aenean massa. Cum sociis natoque penatibus et magnis dis parturient montes, nascetur ridiculus mus. Donec quam felis, ultricies nec, pellentesque eu, pretium quis, sem. Nulla consequat massa quis enim. Donec pede justo, fringilla vel, aliquet nec, vulputate eget, arcu. In enim justo, rhoncus ut, imperdiet a, venenatis vitae, justo. Nullam dictum felis eu pede mollis pretium. Integer tincidunt. Cras dapibus. Vivamus elementum semper nisi. Aenean vulputate eleifend tellus. Aenean leo ligula, porttitor eu, consequat vitae, eleifend ac, enim. Aliquam lorem ante, dapibus in, viverra quis, feugiat a, tellus. Phasellus viverra nulla ut metus varius laoreet. Quisque rutrum. Aenean imperdiet. Etiam ultricies nisi vel augue. Curabitur ullamcorper ultricies nisi. Nam eget dui. Etiam rhoncus. Maecenas tempus, tellus eget condimentum rhoncus, sem quam semper libero, sit amet adipiscing sem neque sed ipsum. Nam quam nunc, blandit vel, luctus pulvinar, hendrerit id, lorem. Maecenas nec odio et ante tincidunt tempus. Donec vitae sapien ut libero venenatis faucibus. Nullam quis ante. Etiam sit amet orci eget eros faucibus tincidunt. Duis leo. Sed fringilla mauris sit amet nibh. Donec sodales sagittis magna. Sed consequat, leo eget bibendum sodales, augue velit cursus nunc,",
    "versions":[
      {
        "id":0,
        "title":"3GB-32GB",
        "alias":"3gb-32gb",
        "image":"/upload/Dell Vostro 3400.png" ,
        "price":215.80
      },{
        "id":1,
        "title":"4GB-64GB",
        "alias":"4gb-64gb",
        "image":"/upload/Dell Vostro 3400.png" ,
        "price":258.96
      }
    ],
      "albums":[
        {
          "image":"/upload/Dell Vostro 3400.png"
        },
        {
          "image":"/upload/Dell Vostro 3400.png"
        },
        {
          "image":"/upload/Dell Vostro 3400.png"
        },
        {
          "image":"/upload/Dell Vostro 3400.png"
        },
        {
          "image":"/upload/Dell Vostro 3400.png"
        }
      ]
  }
,{
    "id":9,
    "title":"GIGABYTE Gaming G5",
    "alias":"gigabyte-gaming-g5",
    "rating":3.8141911772669532,
    "content":"Lorem ipsum dolor sit amet, consectetuer adipiscing elit. Aenean commodo ligula eget dolor. Aenean massa. Cum sociis natoque penatibus et magnis dis parturient montes, nascetur ridiculus mus. Donec quam felis, ultricies nec, pellentesque eu, pretium quis, sem. Nulla consequat massa quis enim. Donec pede justo, fringilla vel, aliquet nec, vulputate eget, arcu. In enim justo, rhoncus ut, imperdiet a, venenatis vitae, justo. Nullam dictum felis eu pede mollis pretium. Integer tincidunt. Cras dapibus. Vivamus elementum semper nisi. Aenean vulputate eleifend tellus. Aenean leo ligula, porttitor eu, consequat vitae, eleifend ac, enim. Aliquam lorem ante, dapibus in, viverra quis, feugiat a, tellus. Phasellus viverra nulla ut metus varius laoreet. Quisque rutrum. Aenean imperdiet. Etiam ultricies nisi vel augue. Curabitur ullamcorper ultricies nisi. Nam eget dui. Etiam rhoncus. Maecenas tempus, tellus eget condimentum rhoncus, sem quam semper libero, sit amet adipiscing sem neque sed ipsum. Nam quam nunc, blandit vel, luctus pulvinar, hendrerit id, lorem. Maecenas nec odio et ante tincidunt tempus. Donec vitae sapien ut libero venenatis faucibus. Nullam quis ante. Etiam sit amet orci eget eros faucibus tincidunt. Duis leo. Sed fringilla mauris sit amet nibh. Donec sodales sagittis magna. Sed consequat, leo eget bibendum sodales, augue velit cursus nunc,",
    "versions":[
      {
        "id":0,
        "title":"3GB-32GB",
        "alias":"3gb-32gb",
        "image":"/upload/GIGABYTE Gaming G5.png" ,
        "price":327.17
      },{
        "id":1,
        "title":"4GB-64GB",
        "alias":"4gb-64gb",
        "image":"/upload/GIGABYTE Gaming G5.png" ,
        "price":392.60 ,
        "salePrice":119.47
      }
    ],
      "albums":[
        {
          "image":"/upload/GIGABYTE Gaming G5.png"
        },
        {
          "image":"/upload/GIGABYTE Gaming G5.png"
        },
        {
          "image":"/upload/GIGABYTE Gaming G5.png"
        },
        {
          "image":"/upload/GIGABYTE Gaming G5.png"
        },
        {
          "image":"/upload/GIGABYTE Gaming G5.png"
        }
      ]
  }
,{
    "id":10,
    "title":"HP Envy 13 ba1031TU",
    "alias":"hp-envy-13-ba1031tu",
    "rating":1.4793413479108064,
    "content":"Lorem ipsum dolor sit amet, consectetuer adipiscing elit. Aenean commodo ligula eget dolor. Aenean massa. Cum sociis natoque penatibus et magnis dis parturient montes, nascetur ridiculus mus. Donec quam felis, ultricies nec, pellentesque eu, pretium quis, sem. Nulla consequat massa quis enim. Donec pede justo, fringilla vel, aliquet nec, vulputate eget, arcu. In enim justo, rhoncus ut, imperdiet a, venenatis vitae, justo. Nullam dictum felis eu pede mollis pretium. Integer tincidunt. Cras dapibus. Vivamus elementum semper nisi. Aenean vulputate eleifend tellus. Aenean leo ligula, porttitor eu, consequat vitae, eleifend ac, enim. Aliquam lorem ante, dapibus in, viverra quis, feugiat a, tellus. Phasellus viverra nulla ut metus varius laoreet. Quisque rutrum. Aenean imperdiet. Etiam ultricies nisi vel augue. Curabitur ullamcorper ultricies nisi. Nam eget dui. Etiam rhoncus. Maecenas tempus, tellus eget condimentum rhoncus, sem quam semper libero, sit amet adipiscing sem neque sed ipsum. Nam quam nunc, blandit vel, luctus pulvinar, hendrerit id, lorem. Maecenas nec odio et ante tincidunt tempus. Donec vitae sapien ut libero venenatis faucibus. Nullam quis ante. Etiam sit amet orci eget eros faucibus tincidunt. Duis leo. Sed fringilla mauris sit amet nibh. Donec sodales sagittis magna. Sed consequat, leo eget bibendum sodales, augue velit cursus nunc,",
    "versions":[
      {
        "id":0,
        "title":"3GB-32GB",
        "alias":"3gb-32gb",
        "image":"/upload/HP Envy 13 ba1031TU.png" ,
        "price":294.97
      },{
        "id":1,
        "title":"4GB-64GB",
        "alias":"4gb-64gb",
        "image":"/upload/HP Envy 13 ba1031TU.png" ,
        "price":353.96
      }
    ],
      "albums":[
        {
          "image":"/upload/HP Envy 13 ba1031TU.png"
        },
        {
          "image":"/upload/HP Envy 13 ba1031TU.png"
        },
        {
          "image":"/upload/HP Envy 13 ba1031TU.png"
        },
        {
          "image":"/upload/HP Envy 13 ba1031TU.png"
        },
        {
          "image":"/upload/HP Envy 13 ba1031TU.png"
        }
      ]
  }
,{
    "id":11,
    "title":"HP Gaming VICTUS 16",
    "alias":"hp-gaming-victus-16",
    "rating":3.6540767711576483,
    "content":"Lorem ipsum dolor sit amet, consectetuer adipiscing elit. Aenean commodo ligula eget dolor. Aenean massa. Cum sociis natoque penatibus et magnis dis parturient montes, nascetur ridiculus mus. Donec quam felis, ultricies nec, pellentesque eu, pretium quis, sem. Nulla consequat massa quis enim. Donec pede justo, fringilla vel, aliquet nec, vulputate eget, arcu. In enim justo, rhoncus ut, imperdiet a, venenatis vitae, justo. Nullam dictum felis eu pede mollis pretium. Integer tincidunt. Cras dapibus. Vivamus elementum semper nisi. Aenean vulputate eleifend tellus. Aenean leo ligula, porttitor eu, consequat vitae, eleifend ac, enim. Aliquam lorem ante, dapibus in, viverra quis, feugiat a, tellus. Phasellus viverra nulla ut metus varius laoreet. Quisque rutrum. Aenean imperdiet. Etiam ultricies nisi vel augue. Curabitur ullamcorper ultricies nisi. Nam eget dui. Etiam rhoncus. Maecenas tempus, tellus eget condimentum rhoncus, sem quam semper libero, sit amet adipiscing sem neque sed ipsum. Nam quam nunc, blandit vel, luctus pulvinar, hendrerit id, lorem. Maecenas nec odio et ante tincidunt tempus. Donec vitae sapien ut libero venenatis faucibus. Nullam quis ante. Etiam sit amet orci eget eros faucibus tincidunt. Duis leo. Sed fringilla mauris sit amet nibh. Donec sodales sagittis magna. Sed consequat, leo eget bibendum sodales, augue velit cursus nunc,",
    "versions":[
      {
        "id":0,
        "title":"3GB-32GB",
        "alias":"3gb-32gb",
        "image":"/upload/HP Gaming VICTUS 16.png" ,
        "price":72.80 ,
        "salePrice":26.20
      },{
        "id":1,
        "title":"4GB-64GB",
        "alias":"4gb-64gb",
        "image":"/upload/HP Gaming VICTUS 16.png" ,
        "price":87.36 ,
        "salePrice":30.77
      }
    ],
      "albums":[
        {
          "image":"/upload/HP Gaming VICTUS 16.png"
        },
        {
          "image":"/upload/HP Gaming VICTUS 16.png"
        },
        {
          "image":"/upload/HP Gaming VICTUS 16.png"
        },
        {
          "image":"/upload/HP Gaming VICTUS 16.png"
        },
        {
          "image":"/upload/HP Gaming VICTUS 16.png"
        }
      ]
  }
,{
    "id":12,
    "title":"iPhone 11",
    "alias":"iphone-11",
    "rating":1.8961491601275104,
    "content":"Lorem ipsum dolor sit amet, consectetuer adipiscing elit. Aenean commodo ligula eget dolor. Aenean massa. Cum sociis natoque penatibus et magnis dis parturient montes, nascetur ridiculus mus. Donec quam felis, ultricies nec, pellentesque eu, pretium quis, sem. Nulla consequat massa quis enim. Donec pede justo, fringilla vel, aliquet nec, vulputate eget, arcu. In enim justo, rhoncus ut, imperdiet a, venenatis vitae, justo. Nullam dictum felis eu pede mollis pretium. Integer tincidunt. Cras dapibus. Vivamus elementum semper nisi. Aenean vulputate eleifend tellus. Aenean leo ligula, porttitor eu, consequat vitae, eleifend ac, enim. Aliquam lorem ante, dapibus in, viverra quis, feugiat a, tellus. Phasellus viverra nulla ut metus varius laoreet. Quisque rutrum. Aenean imperdiet. Etiam ultricies nisi vel augue. Curabitur ullamcorper ultricies nisi. Nam eget dui. Etiam rhoncus. Maecenas tempus, tellus eget condimentum rhoncus, sem quam semper libero, sit amet adipiscing sem neque sed ipsum. Nam quam nunc, blandit vel, luctus pulvinar, hendrerit id, lorem. Maecenas nec odio et ante tincidunt tempus. Donec vitae sapien ut libero venenatis faucibus. Nullam quis ante. Etiam sit amet orci eget eros faucibus tincidunt. Duis leo. Sed fringilla mauris sit amet nibh. Donec sodales sagittis magna. Sed consequat, leo eget bibendum sodales, augue velit cursus nunc,",
    "versions":[
      {
        "id":0,
        "title":"3GB-32GB",
        "alias":"3gb-32gb",
        "image":"/upload/iPhone 11.png" ,
        "price":375.54 ,
        "salePrice":116.43
      },{
        "id":1,
        "title":"4GB-64GB",
        "alias":"4gb-64gb",
        "image":"/upload/iPhone 11.png" ,
        "price":450.65
      }
    ],
      "albums":[
        {
          "image":"/upload/iPhone 11.png"
        },
        {
          "image":"/upload/iPhone 11.png"
        },
        {
          "image":"/upload/iPhone 11.png"
        },
        {
          "image":"/upload/iPhone 11.png"
        },
        {
          "image":"/upload/iPhone 11.png"
        }
      ]
  }
,{
    "id":13,
    "title":"iPhone 12 Pro",
    "alias":"iphone-12-pro",
    "rating":4.9594512238395785,
    "content":"Lorem ipsum dolor sit amet, consectetuer adipiscing elit. Aenean commodo ligula eget dolor. Aenean massa. Cum sociis natoque penatibus et magnis dis parturient montes, nascetur ridiculus mus. Donec quam felis, ultricies nec, pellentesque eu, pretium quis, sem. Nulla consequat massa quis enim. Donec pede justo, fringilla vel, aliquet nec, vulputate eget, arcu. In enim justo, rhoncus ut, imperdiet a, venenatis vitae, justo. Nullam dictum felis eu pede mollis pretium. Integer tincidunt. Cras dapibus. Vivamus elementum semper nisi. Aenean vulputate eleifend tellus. Aenean leo ligula, porttitor eu, consequat vitae, eleifend ac, enim. Aliquam lorem ante, dapibus in, viverra quis, feugiat a, tellus. Phasellus viverra nulla ut metus varius laoreet. Quisque rutrum. Aenean imperdiet. Etiam ultricies nisi vel augue. Curabitur ullamcorper ultricies nisi. Nam eget dui. Etiam rhoncus. Maecenas tempus, tellus eget condimentum rhoncus, sem quam semper libero, sit amet adipiscing sem neque sed ipsum. Nam quam nunc, blandit vel, luctus pulvinar, hendrerit id, lorem. Maecenas nec odio et ante tincidunt tempus. Donec vitae sapien ut libero venenatis faucibus. Nullam quis ante. Etiam sit amet orci eget eros faucibus tincidunt. Duis leo. Sed fringilla mauris sit amet nibh. Donec sodales sagittis magna. Sed consequat, leo eget bibendum sodales, augue velit cursus nunc,",
    "versions":[
      {
        "id":0,
        "title":"3GB-32GB",
        "alias":"3gb-32gb",
        "image":"/upload/iPhone 12 Pro.png"
      },{
        "id":1,
        "title":"4GB-64GB",
        "alias":"4gb-64gb",
        "image":"/upload/iPhone 12 Pro.png"
      }
    ],
      "albums":[
        {
          "image":"/upload/iPhone 12 Pro.png"
        },
        {
          "image":"/upload/iPhone 12 Pro.png"
        },
        {
          "image":"/upload/iPhone 12 Pro.png"
        },
        {
          "image":"/upload/iPhone 12 Pro.png"
        },
        {
          "image":"/upload/iPhone 12 Pro.png"
        }
      ]
  }
,{
    "id":14,
    "title":"iPhone 13 Mini",
    "alias":"iphone-13-mini",
    "rating":4.3891669039408585,
    "content":"Lorem ipsum dolor sit amet, consectetuer adipiscing elit. Aenean commodo ligula eget dolor. Aenean massa. Cum sociis natoque penatibus et magnis dis parturient montes, nascetur ridiculus mus. Donec quam felis, ultricies nec, pellentesque eu, pretium quis, sem. Nulla consequat massa quis enim. Donec pede justo, fringilla vel, aliquet nec, vulputate eget, arcu. In enim justo, rhoncus ut, imperdiet a, venenatis vitae, justo. Nullam dictum felis eu pede mollis pretium. Integer tincidunt. Cras dapibus. Vivamus elementum semper nisi. Aenean vulputate eleifend tellus. Aenean leo ligula, porttitor eu, consequat vitae, eleifend ac, enim. Aliquam lorem ante, dapibus in, viverra quis, feugiat a, tellus. Phasellus viverra nulla ut metus varius laoreet. Quisque rutrum. Aenean imperdiet. Etiam ultricies nisi vel augue. Curabitur ullamcorper ultricies nisi. Nam eget dui. Etiam rhoncus. Maecenas tempus, tellus eget condimentum rhoncus, sem quam semper libero, sit amet adipiscing sem neque sed ipsum. Nam quam nunc, blandit vel, luctus pulvinar, hendrerit id, lorem. Maecenas nec odio et ante tincidunt tempus. Donec vitae sapien ut libero venenatis faucibus. Nullam quis ante. Etiam sit amet orci eget eros faucibus tincidunt. Duis leo. Sed fringilla mauris sit amet nibh. Donec sodales sagittis magna. Sed consequat, leo eget bibendum sodales, augue velit cursus nunc,",
    "versions":[
      {
        "id":0,
        "title":"3GB-32GB",
        "alias":"3gb-32gb",
        "image":"/upload/iPhone 13 Mini.png" ,
        "price":384.59
      },{
        "id":1,
        "title":"4GB-64GB",
        "alias":"4gb-64gb",
        "image":"/upload/iPhone 13 Mini.png" ,
        "price":461.51 ,
        "salePrice":214.50
      }
    ],
      "albums":[
        {
          "image":"/upload/iPhone 13 Mini.png"
        },
        {
          "image":"/upload/iPhone 13 Mini.png"
        },
        {
          "image":"/upload/iPhone 13 Mini.png"
        },
        {
          "image":"/upload/iPhone 13 Mini.png"
        },
        {
          "image":"/upload/iPhone 13 Mini.png"
        }
      ]
  }
,{
    "id":15,
    "title":"iPhone 13 Pro Max",
    "alias":"iphone-13-pro-max",
    "rating":3.4430914724928865,
    "content":"Lorem ipsum dolor sit amet, consectetuer adipiscing elit. Aenean commodo ligula eget dolor. Aenean massa. Cum sociis natoque penatibus et magnis dis parturient montes, nascetur ridiculus mus. Donec quam felis, ultricies nec, pellentesque eu, pretium quis, sem. Nulla consequat massa quis enim. Donec pede justo, fringilla vel, aliquet nec, vulputate eget, arcu. In enim justo, rhoncus ut, imperdiet a, venenatis vitae, justo. Nullam dictum felis eu pede mollis pretium. Integer tincidunt. Cras dapibus. Vivamus elementum semper nisi. Aenean vulputate eleifend tellus. Aenean leo ligula, porttitor eu, consequat vitae, eleifend ac, enim. Aliquam lorem ante, dapibus in, viverra quis, feugiat a, tellus. Phasellus viverra nulla ut metus varius laoreet. Quisque rutrum. Aenean imperdiet. Etiam ultricies nisi vel augue. Curabitur ullamcorper ultricies nisi. Nam eget dui. Etiam rhoncus. Maecenas tempus, tellus eget condimentum rhoncus, sem quam semper libero, sit amet adipiscing sem neque sed ipsum. Nam quam nunc, blandit vel, luctus pulvinar, hendrerit id, lorem. Maecenas nec odio et ante tincidunt tempus. Donec vitae sapien ut libero venenatis faucibus. Nullam quis ante. Etiam sit amet orci eget eros faucibus tincidunt. Duis leo. Sed fringilla mauris sit amet nibh. Donec sodales sagittis magna. Sed consequat, leo eget bibendum sodales, augue velit cursus nunc,",
    "versions":[
      {
        "id":0,
        "title":"3GB-32GB",
        "alias":"3gb-32gb",
        "image":"/upload/iPhone 13 Pro Max.png" ,
        "price":59.58 ,
        "salePrice":24.40
      },{
        "id":1,
        "title":"4GB-64GB",
        "alias":"4gb-64gb",
        "image":"/upload/iPhone 13 Pro Max.png" ,
        "price":71.50 ,
        "salePrice":35.47
      }
    ],
      "albums":[
        {
          "image":"/upload/iPhone 13 Pro Max.png"
        },
        {
          "image":"/upload/iPhone 13 Pro Max.png"
        },
        {
          "image":"/upload/iPhone 13 Pro Max.png"
        },
        {
          "image":"/upload/iPhone 13 Pro Max.png"
        },
        {
          "image":"/upload/iPhone 13 Pro Max.png"
        }
      ]
  }
,{
    "id":16,
    "title":"iPhone SE",
    "alias":"iphone-se",
    "rating":2.853886796636238,
    "content":"Lorem ipsum dolor sit amet, consectetuer adipiscing elit. Aenean commodo ligula eget dolor. Aenean massa. Cum sociis natoque penatibus et magnis dis parturient montes, nascetur ridiculus mus. Donec quam felis, ultricies nec, pellentesque eu, pretium quis, sem. Nulla consequat massa quis enim. Donec pede justo, fringilla vel, aliquet nec, vulputate eget, arcu. In enim justo, rhoncus ut, imperdiet a, venenatis vitae, justo. Nullam dictum felis eu pede mollis pretium. Integer tincidunt. Cras dapibus. Vivamus elementum semper nisi. Aenean vulputate eleifend tellus. Aenean leo ligula, porttitor eu, consequat vitae, eleifend ac, enim. Aliquam lorem ante, dapibus in, viverra quis, feugiat a, tellus. Phasellus viverra nulla ut metus varius laoreet. Quisque rutrum. Aenean imperdiet. Etiam ultricies nisi vel augue. Curabitur ullamcorper ultricies nisi. Nam eget dui. Etiam rhoncus. Maecenas tempus, tellus eget condimentum rhoncus, sem quam semper libero, sit amet adipiscing sem neque sed ipsum. Nam quam nunc, blandit vel, luctus pulvinar, hendrerit id, lorem. Maecenas nec odio et ante tincidunt tempus. Donec vitae sapien ut libero venenatis faucibus. Nullam quis ante. Etiam sit amet orci eget eros faucibus tincidunt. Duis leo. Sed fringilla mauris sit amet nibh. Donec sodales sagittis magna. Sed consequat, leo eget bibendum sodales, augue velit cursus nunc,",
    "versions":[
      {
        "id":0,
        "title":"3GB-32GB",
        "alias":"3gb-32gb",
        "image":"/upload/iPhone SE.png"
      },{
        "id":1,
        "title":"4GB-64GB",
        "alias":"4gb-64gb",
        "image":"/upload/iPhone SE.png"
      }
    ],
      "albums":[
        {
          "image":"/upload/iPhone SE.png"
        },
        {
          "image":"/upload/iPhone SE.png"
        },
        {
          "image":"/upload/iPhone SE.png"
        },
        {
          "image":"/upload/iPhone SE.png"
        },
        {
          "image":"/upload/iPhone SE.png"
        }
      ]
  }
,{
    "id":17,
    "title":"iPhone XR",
    "alias":"iphone-xr",
    "rating":2.2401617818088138,
    "content":"Lorem ipsum dolor sit amet, consectetuer adipiscing elit. Aenean commodo ligula eget dolor. Aenean massa. Cum sociis natoque penatibus et magnis dis parturient montes, nascetur ridiculus mus. Donec quam felis, ultricies nec, pellentesque eu, pretium quis, sem. Nulla consequat massa quis enim. Donec pede justo, fringilla vel, aliquet nec, vulputate eget, arcu. In enim justo, rhoncus ut, imperdiet a, venenatis vitae, justo. Nullam dictum felis eu pede mollis pretium. Integer tincidunt. Cras dapibus. Vivamus elementum semper nisi. Aenean vulputate eleifend tellus. Aenean leo ligula, porttitor eu, consequat vitae, eleifend ac, enim. Aliquam lorem ante, dapibus in, viverra quis, feugiat a, tellus. Phasellus viverra nulla ut metus varius laoreet. Quisque rutrum. Aenean imperdiet. Etiam ultricies nisi vel augue. Curabitur ullamcorper ultricies nisi. Nam eget dui. Etiam rhoncus. Maecenas tempus, tellus eget condimentum rhoncus, sem quam semper libero, sit amet adipiscing sem neque sed ipsum. Nam quam nunc, blandit vel, luctus pulvinar, hendrerit id, lorem. Maecenas nec odio et ante tincidunt tempus. Donec vitae sapien ut libero venenatis faucibus. Nullam quis ante. Etiam sit amet orci eget eros faucibus tincidunt. Duis leo. Sed fringilla mauris sit amet nibh. Donec sodales sagittis magna. Sed consequat, leo eget bibendum sodales, augue velit cursus nunc,",
    "versions":[
      {
        "id":0,
        "title":"3GB-32GB",
        "alias":"3gb-32gb",
        "image":"/upload/iPhone XR.png" ,
        "price":246.14
      },{
        "id":1,
        "title":"4GB-64GB",
        "alias":"4gb-64gb",
        "image":"/upload/iPhone XR.png" ,
        "price":295.37
      }
    ],
      "albums":[
        {
          "image":"/upload/iPhone XR.png"
        },
        {
          "image":"/upload/iPhone XR.png"
        },
        {
          "image":"/upload/iPhone XR.png"
        },
        {
          "image":"/upload/iPhone XR.png"
        },
        {
          "image":"/upload/iPhone XR.png"
        }
      ]
  }
,{
    "id":18,
    "title":"MacBook Air M1",
    "alias":"macbook-air-m1",
    "rating":0.2698809356277032,
    "content":"Lorem ipsum dolor sit amet, consectetuer adipiscing elit. Aenean commodo ligula eget dolor. Aenean massa. Cum sociis natoque penatibus et magnis dis parturient montes, nascetur ridiculus mus. Donec quam felis, ultricies nec, pellentesque eu, pretium quis, sem. Nulla consequat massa quis enim. Donec pede justo, fringilla vel, aliquet nec, vulputate eget, arcu. In enim justo, rhoncus ut, imperdiet a, venenatis vitae, justo. Nullam dictum felis eu pede mollis pretium. Integer tincidunt. Cras dapibus. Vivamus elementum semper nisi. Aenean vulputate eleifend tellus. Aenean leo ligula, porttitor eu, consequat vitae, eleifend ac, enim. Aliquam lorem ante, dapibus in, viverra quis, feugiat a, tellus. Phasellus viverra nulla ut metus varius laoreet. Quisque rutrum. Aenean imperdiet. Etiam ultricies nisi vel augue. Curabitur ullamcorper ultricies nisi. Nam eget dui. Etiam rhoncus. Maecenas tempus, tellus eget condimentum rhoncus, sem quam semper libero, sit amet adipiscing sem neque sed ipsum. Nam quam nunc, blandit vel, luctus pulvinar, hendrerit id, lorem. Maecenas nec odio et ante tincidunt tempus. Donec vitae sapien ut libero venenatis faucibus. Nullam quis ante. Etiam sit amet orci eget eros faucibus tincidunt. Duis leo. Sed fringilla mauris sit amet nibh. Donec sodales sagittis magna. Sed consequat, leo eget bibendum sodales, augue velit cursus nunc,",
    "versions":[
      {
        "id":0,
        "title":"3GB-32GB",
        "alias":"3gb-32gb",
        "image":"/upload/MacBook Air M1.png" ,
        "price":43.08 ,
        "salePrice":9.85
      },{
        "id":1,
        "title":"4GB-64GB",
        "alias":"4gb-64gb",
        "image":"/upload/MacBook Air M1.png" ,
        "price":51.70
      }
    ],
      "albums":[
        {
          "image":"/upload/MacBook Air M1.png"
        },
        {
          "image":"/upload/MacBook Air M1.png"
        },
        {
          "image":"/upload/MacBook Air M1.png"
        },
        {
          "image":"/upload/MacBook Air M1.png"
        },
        {
          "image":"/upload/MacBook Air M1.png"
        }
      ]
  }
,{
    "id":19,
    "title":"MacBook Pro M1",
    "alias":"macbook-pro-m1",
    "rating":0.4420774782179626,
    "content":"Lorem ipsum dolor sit amet, consectetuer adipiscing elit. Aenean commodo ligula eget dolor. Aenean massa. Cum sociis natoque penatibus et magnis dis parturient montes, nascetur ridiculus mus. Donec quam felis, ultricies nec, pellentesque eu, pretium quis, sem. Nulla consequat massa quis enim. Donec pede justo, fringilla vel, aliquet nec, vulputate eget, arcu. In enim justo, rhoncus ut, imperdiet a, venenatis vitae, justo. Nullam dictum felis eu pede mollis pretium. Integer tincidunt. Cras dapibus. Vivamus elementum semper nisi. Aenean vulputate eleifend tellus. Aenean leo ligula, porttitor eu, consequat vitae, eleifend ac, enim. Aliquam lorem ante, dapibus in, viverra quis, feugiat a, tellus. Phasellus viverra nulla ut metus varius laoreet. Quisque rutrum. Aenean imperdiet. Etiam ultricies nisi vel augue. Curabitur ullamcorper ultricies nisi. Nam eget dui. Etiam rhoncus. Maecenas tempus, tellus eget condimentum rhoncus, sem quam semper libero, sit amet adipiscing sem neque sed ipsum. Nam quam nunc, blandit vel, luctus pulvinar, hendrerit id, lorem. Maecenas nec odio et ante tincidunt tempus. Donec vitae sapien ut libero venenatis faucibus. Nullam quis ante. Etiam sit amet orci eget eros faucibus tincidunt. Duis leo. Sed fringilla mauris sit amet nibh. Donec sodales sagittis magna. Sed consequat, leo eget bibendum sodales, augue velit cursus nunc,",
    "versions":[
      {
        "id":0,
        "title":"3GB-32GB",
        "alias":"3gb-32gb",
        "image":"/upload/MacBook Pro M1.png" ,
        "price":286.10
      },{
        "id":1,
        "title":"4GB-64GB",
        "alias":"4gb-64gb",
        "image":"/upload/MacBook Pro M1.png" ,
        "price":343.32
      }
    ],
      "albums":[
        {
          "image":"/upload/MacBook Pro M1.png"
        },
        {
          "image":"/upload/MacBook Pro M1.png"
        },
        {
          "image":"/upload/MacBook Pro M1.png"
        },
        {
          "image":"/upload/MacBook Pro M1.png"
        },
        {
          "image":"/upload/MacBook Pro M1.png"
        }
      ]
  }
,{
    "id":20,
    "title":"MSI Gaming GE66 Raider 11UG",
    "alias":"msi-gaming-ge66-raider-11ug",
    "rating":2.5264458368937435,
    "content":"Lorem ipsum dolor sit amet, consectetuer adipiscing elit. Aenean commodo ligula eget dolor. Aenean massa. Cum sociis natoque penatibus et magnis dis parturient montes, nascetur ridiculus mus. Donec quam felis, ultricies nec, pellentesque eu, pretium quis, sem. Nulla consequat massa quis enim. Donec pede justo, fringilla vel, aliquet nec, vulputate eget, arcu. In enim justo, rhoncus ut, imperdiet a, venenatis vitae, justo. Nullam dictum felis eu pede mollis pretium. Integer tincidunt. Cras dapibus. Vivamus elementum semper nisi. Aenean vulputate eleifend tellus. Aenean leo ligula, porttitor eu, consequat vitae, eleifend ac, enim. Aliquam lorem ante, dapibus in, viverra quis, feugiat a, tellus. Phasellus viverra nulla ut metus varius laoreet. Quisque rutrum. Aenean imperdiet. Etiam ultricies nisi vel augue. Curabitur ullamcorper ultricies nisi. Nam eget dui. Etiam rhoncus. Maecenas tempus, tellus eget condimentum rhoncus, sem quam semper libero, sit amet adipiscing sem neque sed ipsum. Nam quam nunc, blandit vel, luctus pulvinar, hendrerit id, lorem. Maecenas nec odio et ante tincidunt tempus. Donec vitae sapien ut libero venenatis faucibus. Nullam quis ante. Etiam sit amet orci eget eros faucibus tincidunt. Duis leo. Sed fringilla mauris sit amet nibh. Donec sodales sagittis magna. Sed consequat, leo eget bibendum sodales, augue velit cursus nunc,",
    "versions":[
      {
        "id":0,
        "title":"3GB-32GB",
        "alias":"3gb-32gb",
        "image":"/upload/MSI Gaming GE66 Raider 11UG.png" ,
        "price":25.13
      },{
        "id":1,
        "title":"4GB-64GB",
        "alias":"4gb-64gb",
        "image":"/upload/MSI Gaming GE66 Raider 11UG.png" ,
        "price":30.16 ,
        "salePrice":14.41
      }
    ],
      "albums":[
        {
          "image":"/upload/MSI Gaming GE66 Raider 11UG.png"
        },
        {
          "image":"/upload/MSI Gaming GE66 Raider 11UG.png"
        },
        {
          "image":"/upload/MSI Gaming GE66 Raider 11UG.png"
        },
        {
          "image":"/upload/MSI Gaming GE66 Raider 11UG.png"
        },
        {
          "image":"/upload/MSI Gaming GE66 Raider 11UG.png"
        }
      ]
  }
,{
    "id":21,
    "title":"MSI Gaming GE66 Raider 11UH",
    "alias":"msi-gaming-ge66-raider-11uh",
    "rating":4.249399516054058,
    "content":"Lorem ipsum dolor sit amet, consectetuer adipiscing elit. Aenean commodo ligula eget dolor. Aenean massa. Cum sociis natoque penatibus et magnis dis parturient montes, nascetur ridiculus mus. Donec quam felis, ultricies nec, pellentesque eu, pretium quis, sem. Nulla consequat massa quis enim. Donec pede justo, fringilla vel, aliquet nec, vulputate eget, arcu. In enim justo, rhoncus ut, imperdiet a, venenatis vitae, justo. Nullam dictum felis eu pede mollis pretium. Integer tincidunt. Cras dapibus. Vivamus elementum semper nisi. Aenean vulputate eleifend tellus. Aenean leo ligula, porttitor eu, consequat vitae, eleifend ac, enim. Aliquam lorem ante, dapibus in, viverra quis, feugiat a, tellus. Phasellus viverra nulla ut metus varius laoreet. Quisque rutrum. Aenean imperdiet. Etiam ultricies nisi vel augue. Curabitur ullamcorper ultricies nisi. Nam eget dui. Etiam rhoncus. Maecenas tempus, tellus eget condimentum rhoncus, sem quam semper libero, sit amet adipiscing sem neque sed ipsum. Nam quam nunc, blandit vel, luctus pulvinar, hendrerit id, lorem. Maecenas nec odio et ante tincidunt tempus. Donec vitae sapien ut libero venenatis faucibus. Nullam quis ante. Etiam sit amet orci eget eros faucibus tincidunt. Duis leo. Sed fringilla mauris sit amet nibh. Donec sodales sagittis magna. Sed consequat, leo eget bibendum sodales, augue velit cursus nunc,",
    "versions":[
      {
        "id":0,
        "title":"3GB-32GB",
        "alias":"3gb-32gb",
        "image":"/upload/MSI Gaming GE66 Raider 11UH.png"
      },{
        "id":1,
        "title":"4GB-64GB",
        "alias":"4gb-64gb",
        "image":"/upload/MSI Gaming GE66 Raider 11UH.png"
      }
    ],
      "albums":[
        {
          "image":"/upload/MSI Gaming GE66 Raider 11UH.png"
        },
        {
          "image":"/upload/MSI Gaming GE66 Raider 11UH.png"
        },
        {
          "image":"/upload/MSI Gaming GE66 Raider 11UH.png"
        },
        {
          "image":"/upload/MSI Gaming GE66 Raider 11UH.png"
        },
        {
          "image":"/upload/MSI Gaming GE66 Raider 11UH.png"
        }
      ]
  }
,{
    "id":22,
    "title":"MSI Gaming GF65 Thin 10UE",
    "alias":"msi-gaming-gf65-thin-10ue",
    "rating":1.9577977792642953,
    "content":"Lorem ipsum dolor sit amet, consectetuer adipiscing elit. Aenean commodo ligula eget dolor. Aenean massa. Cum sociis natoque penatibus et magnis dis parturient montes, nascetur ridiculus mus. Donec quam felis, ultricies nec, pellentesque eu, pretium quis, sem. Nulla consequat massa quis enim. Donec pede justo, fringilla vel, aliquet nec, vulputate eget, arcu. In enim justo, rhoncus ut, imperdiet a, venenatis vitae, justo. Nullam dictum felis eu pede mollis pretium. Integer tincidunt. Cras dapibus. Vivamus elementum semper nisi. Aenean vulputate eleifend tellus. Aenean leo ligula, porttitor eu, consequat vitae, eleifend ac, enim. Aliquam lorem ante, dapibus in, viverra quis, feugiat a, tellus. Phasellus viverra nulla ut metus varius laoreet. Quisque rutrum. Aenean imperdiet. Etiam ultricies nisi vel augue. Curabitur ullamcorper ultricies nisi. Nam eget dui. Etiam rhoncus. Maecenas tempus, tellus eget condimentum rhoncus, sem quam semper libero, sit amet adipiscing sem neque sed ipsum. Nam quam nunc, blandit vel, luctus pulvinar, hendrerit id, lorem. Maecenas nec odio et ante tincidunt tempus. Donec vitae sapien ut libero venenatis faucibus. Nullam quis ante. Etiam sit amet orci eget eros faucibus tincidunt. Duis leo. Sed fringilla mauris sit amet nibh. Donec sodales sagittis magna. Sed consequat, leo eget bibendum sodales, augue velit cursus nunc,",
    "versions":[
      {
        "id":0,
        "title":"3GB-32GB",
        "alias":"3gb-32gb",
        "image":"/upload/MSI Gaming GF65 Thin 10UE.png" ,
        "price":31.03
      },{
        "id":1,
        "title":"4GB-64GB",
        "alias":"4gb-64gb",
        "image":"/upload/MSI Gaming GF65 Thin 10UE.png" ,
        "price":37.24
      }
    ],
      "albums":[
        {
          "image":"/upload/MSI Gaming GF65 Thin 10UE.png"
        },
        {
          "image":"/upload/MSI Gaming GF65 Thin 10UE.png"
        },
        {
          "image":"/upload/MSI Gaming GF65 Thin 10UE.png"
        },
        {
          "image":"/upload/MSI Gaming GF65 Thin 10UE.png"
        },
        {
          "image":"/upload/MSI Gaming GF65 Thin 10UE.png"
        }
      ]
  }
,{
    "id":23,
    "title":"MSI Gaming GS66 Stealth 11UG",
    "alias":"msi-gaming-gs66-stealth-11ug",
    "rating":2.345161745038171,
    "content":"Lorem ipsum dolor sit amet, consectetuer adipiscing elit. Aenean commodo ligula eget dolor. Aenean massa. Cum sociis natoque penatibus et magnis dis parturient montes, nascetur ridiculus mus. Donec quam felis, ultricies nec, pellentesque eu, pretium quis, sem. Nulla consequat massa quis enim. Donec pede justo, fringilla vel, aliquet nec, vulputate eget, arcu. In enim justo, rhoncus ut, imperdiet a, venenatis vitae, justo. Nullam dictum felis eu pede mollis pretium. Integer tincidunt. Cras dapibus. Vivamus elementum semper nisi. Aenean vulputate eleifend tellus. Aenean leo ligula, porttitor eu, consequat vitae, eleifend ac, enim. Aliquam lorem ante, dapibus in, viverra quis, feugiat a, tellus. Phasellus viverra nulla ut metus varius laoreet. Quisque rutrum. Aenean imperdiet. Etiam ultricies nisi vel augue. Curabitur ullamcorper ultricies nisi. Nam eget dui. Etiam rhoncus. Maecenas tempus, tellus eget condimentum rhoncus, sem quam semper libero, sit amet adipiscing sem neque sed ipsum. Nam quam nunc, blandit vel, luctus pulvinar, hendrerit id, lorem. Maecenas nec odio et ante tincidunt tempus. Donec vitae sapien ut libero venenatis faucibus. Nullam quis ante. Etiam sit amet orci eget eros faucibus tincidunt. Duis leo. Sed fringilla mauris sit amet nibh. Donec sodales sagittis magna. Sed consequat, leo eget bibendum sodales, augue velit cursus nunc,",
    "versions":[
      {
        "id":0,
        "title":"3GB-32GB",
        "alias":"3gb-32gb",
        "image":"/upload/MSI Gaming GS66 Stealth 11UG.png" ,
        "price":54.76 ,
        "salePrice":23.82
      },{
        "id":1,
        "title":"4GB-64GB",
        "alias":"4gb-64gb",
        "image":"/upload/MSI Gaming GS66 Stealth 11UG.png" ,
        "price":65.71 ,
        "salePrice":17.36
      }
    ],
      "albums":[
        {
          "image":"/upload/MSI Gaming GS66 Stealth 11UG.png"
        },
        {
          "image":"/upload/MSI Gaming GS66 Stealth 11UG.png"
        },
        {
          "image":"/upload/MSI Gaming GS66 Stealth 11UG.png"
        },
        {
          "image":"/upload/MSI Gaming GS66 Stealth 11UG.png"
        },
        {
          "image":"/upload/MSI Gaming GS66 Stealth 11UG.png"
        }
      ]
  }
,{
    "id":24,
    "title":"MSI Modern 15 A11MU",
    "alias":"msi-modern-15-a11mu",
    "rating":0.8114296324826875,
    "content":"Lorem ipsum dolor sit amet, consectetuer adipiscing elit. Aenean commodo ligula eget dolor. Aenean massa. Cum sociis natoque penatibus et magnis dis parturient montes, nascetur ridiculus mus. Donec quam felis, ultricies nec, pellentesque eu, pretium quis, sem. Nulla consequat massa quis enim. Donec pede justo, fringilla vel, aliquet nec, vulputate eget, arcu. In enim justo, rhoncus ut, imperdiet a, venenatis vitae, justo. Nullam dictum felis eu pede mollis pretium. Integer tincidunt. Cras dapibus. Vivamus elementum semper nisi. Aenean vulputate eleifend tellus. Aenean leo ligula, porttitor eu, consequat vitae, eleifend ac, enim. Aliquam lorem ante, dapibus in, viverra quis, feugiat a, tellus. Phasellus viverra nulla ut metus varius laoreet. Quisque rutrum. Aenean imperdiet. Etiam ultricies nisi vel augue. Curabitur ullamcorper ultricies nisi. Nam eget dui. Etiam rhoncus. Maecenas tempus, tellus eget condimentum rhoncus, sem quam semper libero, sit amet adipiscing sem neque sed ipsum. Nam quam nunc, blandit vel, luctus pulvinar, hendrerit id, lorem. Maecenas nec odio et ante tincidunt tempus. Donec vitae sapien ut libero venenatis faucibus. Nullam quis ante. Etiam sit amet orci eget eros faucibus tincidunt. Duis leo. Sed fringilla mauris sit amet nibh. Donec sodales sagittis magna. Sed consequat, leo eget bibendum sodales, augue velit cursus nunc,",
    "versions":[
      {
        "id":0,
        "title":"3GB-32GB",
        "alias":"3gb-32gb",
        "image":"/upload/MSI Modern 15 A11MU.png" ,
        "price":386.66
      },{
        "id":1,
        "title":"4GB-64GB",
        "alias":"4gb-64gb",
        "image":"/upload/MSI Modern 15 A11MU.png" ,
        "price":463.99
      }
    ],
      "albums":[
        {
          "image":"/upload/MSI Modern 15 A11MU.png"
        },
        {
          "image":"/upload/MSI Modern 15 A11MU.png"
        },
        {
          "image":"/upload/MSI Modern 15 A11MU.png"
        },
        {
          "image":"/upload/MSI Modern 15 A11MU.png"
        },
        {
          "image":"/upload/MSI Modern 15 A11MU.png"
        }
      ]
  }
,{
    "id":25,
    "title":"Nokia X10 5G",
    "alias":"nokia-x10-5g",
    "rating":2.9298404883832028,
    "content":"Lorem ipsum dolor sit amet, consectetuer adipiscing elit. Aenean commodo ligula eget dolor. Aenean massa. Cum sociis natoque penatibus et magnis dis parturient montes, nascetur ridiculus mus. Donec quam felis, ultricies nec, pellentesque eu, pretium quis, sem. Nulla consequat massa quis enim. Donec pede justo, fringilla vel, aliquet nec, vulputate eget, arcu. In enim justo, rhoncus ut, imperdiet a, venenatis vitae, justo. Nullam dictum felis eu pede mollis pretium. Integer tincidunt. Cras dapibus. Vivamus elementum semper nisi. Aenean vulputate eleifend tellus. Aenean leo ligula, porttitor eu, consequat vitae, eleifend ac, enim. Aliquam lorem ante, dapibus in, viverra quis, feugiat a, tellus. Phasellus viverra nulla ut metus varius laoreet. Quisque rutrum. Aenean imperdiet. Etiam ultricies nisi vel augue. Curabitur ullamcorper ultricies nisi. Nam eget dui. Etiam rhoncus. Maecenas tempus, tellus eget condimentum rhoncus, sem quam semper libero, sit amet adipiscing sem neque sed ipsum. Nam quam nunc, blandit vel, luctus pulvinar, hendrerit id, lorem. Maecenas nec odio et ante tincidunt tempus. Donec vitae sapien ut libero venenatis faucibus. Nullam quis ante. Etiam sit amet orci eget eros faucibus tincidunt. Duis leo. Sed fringilla mauris sit amet nibh. Donec sodales sagittis magna. Sed consequat, leo eget bibendum sodales, augue velit cursus nunc,",
    "versions":[
      {
        "id":0,
        "title":"3GB-32GB",
        "alias":"3gb-32gb",
        "image":"/upload/Nokia X10 5G.png" ,
        "price":136.23
      },{
        "id":1,
        "title":"4GB-64GB",
        "alias":"4gb-64gb",
        "image":"/upload/Nokia X10 5G.png" ,
        "price":163.48
      }
    ],
      "albums":[
        {
          "image":"/upload/Nokia X10 5G.png"
        },
        {
          "image":"/upload/Nokia X10 5G.png"
        },
        {
          "image":"/upload/Nokia X10 5G.png"
        },
        {
          "image":"/upload/Nokia X10 5G.png"
        },
        {
          "image":"/upload/Nokia X10 5G.png"
        }
      ]
  }
,{
    "id":26,
    "title":"OnePlus 7 Pro",
    "alias":"oneplus-7-pro",
    "rating":3.007096329469068,
    "content":"Lorem ipsum dolor sit amet, consectetuer adipiscing elit. Aenean commodo ligula eget dolor. Aenean massa. Cum sociis natoque penatibus et magnis dis parturient montes, nascetur ridiculus mus. Donec quam felis, ultricies nec, pellentesque eu, pretium quis, sem. Nulla consequat massa quis enim. Donec pede justo, fringilla vel, aliquet nec, vulputate eget, arcu. In enim justo, rhoncus ut, imperdiet a, venenatis vitae, justo. Nullam dictum felis eu pede mollis pretium. Integer tincidunt. Cras dapibus. Vivamus elementum semper nisi. Aenean vulputate eleifend tellus. Aenean leo ligula, porttitor eu, consequat vitae, eleifend ac, enim. Aliquam lorem ante, dapibus in, viverra quis, feugiat a, tellus. Phasellus viverra nulla ut metus varius laoreet. Quisque rutrum. Aenean imperdiet. Etiam ultricies nisi vel augue. Curabitur ullamcorper ultricies nisi. Nam eget dui. Etiam rhoncus. Maecenas tempus, tellus eget condimentum rhoncus, sem quam semper libero, sit amet adipiscing sem neque sed ipsum. Nam quam nunc, blandit vel, luctus pulvinar, hendrerit id, lorem. Maecenas nec odio et ante tincidunt tempus. Donec vitae sapien ut libero venenatis faucibus. Nullam quis ante. Etiam sit amet orci eget eros faucibus tincidunt. Duis leo. Sed fringilla mauris sit amet nibh. Donec sodales sagittis magna. Sed consequat, leo eget bibendum sodales, augue velit cursus nunc,",
    "versions":[
      {
        "id":0,
        "title":"3GB-32GB",
        "alias":"3gb-32gb",
        "image":"/upload/OnePlus 7 Pro.png"
      },{
        "id":1,
        "title":"4GB-64GB",
        "alias":"4gb-64gb",
        "image":"/upload/OnePlus 7 Pro.png"
      }
    ],
      "albums":[
        {
          "image":"/upload/OnePlus 7 Pro.png"
        },
        {
          "image":"/upload/OnePlus 7 Pro.png"
        },
        {
          "image":"/upload/OnePlus 7 Pro.png"
        },
        {
          "image":"/upload/OnePlus 7 Pro.png"
        },
        {
          "image":"/upload/OnePlus 7 Pro.png"
        }
      ]
  }
,{
    "id":27,
    "title":"OnePlus 8 Pro",
    "alias":"oneplus-8-pro",
    "rating":0.27041409751225154,
    "content":"Lorem ipsum dolor sit amet, consectetuer adipiscing elit. Aenean commodo ligula eget dolor. Aenean massa. Cum sociis natoque penatibus et magnis dis parturient montes, nascetur ridiculus mus. Donec quam felis, ultricies nec, pellentesque eu, pretium quis, sem. Nulla consequat massa quis enim. Donec pede justo, fringilla vel, aliquet nec, vulputate eget, arcu. In enim justo, rhoncus ut, imperdiet a, venenatis vitae, justo. Nullam dictum felis eu pede mollis pretium. Integer tincidunt. Cras dapibus. Vivamus elementum semper nisi. Aenean vulputate eleifend tellus. Aenean leo ligula, porttitor eu, consequat vitae, eleifend ac, enim. Aliquam lorem ante, dapibus in, viverra quis, feugiat a, tellus. Phasellus viverra nulla ut metus varius laoreet. Quisque rutrum. Aenean imperdiet. Etiam ultricies nisi vel augue. Curabitur ullamcorper ultricies nisi. Nam eget dui. Etiam rhoncus. Maecenas tempus, tellus eget condimentum rhoncus, sem quam semper libero, sit amet adipiscing sem neque sed ipsum. Nam quam nunc, blandit vel, luctus pulvinar, hendrerit id, lorem. Maecenas nec odio et ante tincidunt tempus. Donec vitae sapien ut libero venenatis faucibus. Nullam quis ante. Etiam sit amet orci eget eros faucibus tincidunt. Duis leo. Sed fringilla mauris sit amet nibh. Donec sodales sagittis magna. Sed consequat, leo eget bibendum sodales, augue velit cursus nunc,",
    "versions":[
      {
        "id":0,
        "title":"3GB-32GB",
        "alias":"3gb-32gb",
        "image":"/upload/OnePlus 8 Pro.png" ,
        "price":252.90
      },{
        "id":1,
        "title":"4GB-64GB",
        "alias":"4gb-64gb",
        "image":"/upload/OnePlus 8 Pro.png" ,
        "price":303.48
      }
    ],
      "albums":[
        {
          "image":"/upload/OnePlus 8 Pro.png"
        },
        {
          "image":"/upload/OnePlus 8 Pro.png"
        },
        {
          "image":"/upload/OnePlus 8 Pro.png"
        },
        {
          "image":"/upload/OnePlus 8 Pro.png"
        },
        {
          "image":"/upload/OnePlus 8 Pro.png"
        }
      ]
  }
,{
    "id":28,
    "title":"OnePlus Nord N10 5G",
    "alias":"oneplus-nord-n10-5g",
    "rating":0.5452785534537696,
    "content":"Lorem ipsum dolor sit amet, consectetuer adipiscing elit. Aenean commodo ligula eget dolor. Aenean massa. Cum sociis natoque penatibus et magnis dis parturient montes, nascetur ridiculus mus. Donec quam felis, ultricies nec, pellentesque eu, pretium quis, sem. Nulla consequat massa quis enim. Donec pede justo, fringilla vel, aliquet nec, vulputate eget, arcu. In enim justo, rhoncus ut, imperdiet a, venenatis vitae, justo. Nullam dictum felis eu pede mollis pretium. Integer tincidunt. Cras dapibus. Vivamus elementum semper nisi. Aenean vulputate eleifend tellus. Aenean leo ligula, porttitor eu, consequat vitae, eleifend ac, enim. Aliquam lorem ante, dapibus in, viverra quis, feugiat a, tellus. Phasellus viverra nulla ut metus varius laoreet. Quisque rutrum. Aenean imperdiet. Etiam ultricies nisi vel augue. Curabitur ullamcorper ultricies nisi. Nam eget dui. Etiam rhoncus. Maecenas tempus, tellus eget condimentum rhoncus, sem quam semper libero, sit amet adipiscing sem neque sed ipsum. Nam quam nunc, blandit vel, luctus pulvinar, hendrerit id, lorem. Maecenas nec odio et ante tincidunt tempus. Donec vitae sapien ut libero venenatis faucibus. Nullam quis ante. Etiam sit amet orci eget eros faucibus tincidunt. Duis leo. Sed fringilla mauris sit amet nibh. Donec sodales sagittis magna. Sed consequat, leo eget bibendum sodales, augue velit cursus nunc,",
    "versions":[
      {
        "id":0,
        "title":"3GB-32GB",
        "alias":"3gb-32gb",
        "image":"/upload/OnePlus Nord N10 5G.png" ,
        "price":327.34
      },{
        "id":1,
        "title":"4GB-64GB",
        "alias":"4gb-64gb",
        "image":"/upload/OnePlus Nord N10 5G.png" ,
        "price":392.81
      }
    ],
      "albums":[
        {
          "image":"/upload/OnePlus Nord N10 5G.png"
        },
        {
          "image":"/upload/OnePlus Nord N10 5G.png"
        },
        {
          "image":"/upload/OnePlus Nord N10 5G.png"
        },
        {
          "image":"/upload/OnePlus Nord N10 5G.png"
        },
        {
          "image":"/upload/OnePlus Nord N10 5G.png"
        }
      ]
  }
,{
    "id":29,
    "title":"OPPO A55",
    "alias":"oppo-a55",
    "rating":1.4519506720747666,
    "content":"Lorem ipsum dolor sit amet, consectetuer adipiscing elit. Aenean commodo ligula eget dolor. Aenean massa. Cum sociis natoque penatibus et magnis dis parturient montes, nascetur ridiculus mus. Donec quam felis, ultricies nec, pellentesque eu, pretium quis, sem. Nulla consequat massa quis enim. Donec pede justo, fringilla vel, aliquet nec, vulputate eget, arcu. In enim justo, rhoncus ut, imperdiet a, venenatis vitae, justo. Nullam dictum felis eu pede mollis pretium. Integer tincidunt. Cras dapibus. Vivamus elementum semper nisi. Aenean vulputate eleifend tellus. Aenean leo ligula, porttitor eu, consequat vitae, eleifend ac, enim. Aliquam lorem ante, dapibus in, viverra quis, feugiat a, tellus. Phasellus viverra nulla ut metus varius laoreet. Quisque rutrum. Aenean imperdiet. Etiam ultricies nisi vel augue. Curabitur ullamcorper ultricies nisi. Nam eget dui. Etiam rhoncus. Maecenas tempus, tellus eget condimentum rhoncus, sem quam semper libero, sit amet adipiscing sem neque sed ipsum. Nam quam nunc, blandit vel, luctus pulvinar, hendrerit id, lorem. Maecenas nec odio et ante tincidunt tempus. Donec vitae sapien ut libero venenatis faucibus. Nullam quis ante. Etiam sit amet orci eget eros faucibus tincidunt. Duis leo. Sed fringilla mauris sit amet nibh. Donec sodales sagittis magna. Sed consequat, leo eget bibendum sodales, augue velit cursus nunc,",
    "versions":[
      {
        "id":0,
        "title":"3GB-32GB",
        "alias":"3gb-32gb",
        "image":"/upload/OPPO A55.png" ,
        "price":388.11 ,
        "salePrice":102.23
      },{
        "id":1,
        "title":"4GB-64GB",
        "alias":"4gb-64gb",
        "image":"/upload/OPPO A55.png" ,
        "price":465.73
      }
    ],
      "albums":[
        {
          "image":"/upload/OPPO A55.png"
        },
        {
          "image":"/upload/OPPO A55.png"
        },
        {
          "image":"/upload/OPPO A55.png"
        },
        {
          "image":"/upload/OPPO A55.png"
        },
        {
          "image":"/upload/OPPO A55.png"
        }
      ]
  }
,{
    "id":30,
    "title":"Oppo A74",
    "alias":"oppo-a74",
    "rating":2.272871211448079,
    "content":"Lorem ipsum dolor sit amet, consectetuer adipiscing elit. Aenean commodo ligula eget dolor. Aenean massa. Cum sociis natoque penatibus et magnis dis parturient montes, nascetur ridiculus mus. Donec quam felis, ultricies nec, pellentesque eu, pretium quis, sem. Nulla consequat massa quis enim. Donec pede justo, fringilla vel, aliquet nec, vulputate eget, arcu. In enim justo, rhoncus ut, imperdiet a, venenatis vitae, justo. Nullam dictum felis eu pede mollis pretium. Integer tincidunt. Cras dapibus. Vivamus elementum semper nisi. Aenean vulputate eleifend tellus. Aenean leo ligula, porttitor eu, consequat vitae, eleifend ac, enim. Aliquam lorem ante, dapibus in, viverra quis, feugiat a, tellus. Phasellus viverra nulla ut metus varius laoreet. Quisque rutrum. Aenean imperdiet. Etiam ultricies nisi vel augue. Curabitur ullamcorper ultricies nisi. Nam eget dui. Etiam rhoncus. Maecenas tempus, tellus eget condimentum rhoncus, sem quam semper libero, sit amet adipiscing sem neque sed ipsum. Nam quam nunc, blandit vel, luctus pulvinar, hendrerit id, lorem. Maecenas nec odio et ante tincidunt tempus. Donec vitae sapien ut libero venenatis faucibus. Nullam quis ante. Etiam sit amet orci eget eros faucibus tincidunt. Duis leo. Sed fringilla mauris sit amet nibh. Donec sodales sagittis magna. Sed consequat, leo eget bibendum sodales, augue velit cursus nunc,",
    "versions":[
      {
        "id":0,
        "title":"3GB-32GB",
        "alias":"3gb-32gb",
        "image":"/upload/Oppo A74.png" ,
        "price":356.87
      },{
        "id":1,
        "title":"4GB-64GB",
        "alias":"4gb-64gb",
        "image":"/upload/Oppo A74.png" ,
        "price":428.24 ,
        "salePrice":167.42
      }
    ],
      "albums":[
        {
          "image":"/upload/Oppo A74.png"
        },
        {
          "image":"/upload/Oppo A74.png"
        },
        {
          "image":"/upload/Oppo A74.png"
        },
        {
          "image":"/upload/Oppo A74.png"
        },
        {
          "image":"/upload/Oppo A74.png"
        }
      ]
  }
,{
    "id":31,
    "title":"OPPO Reno5 5G",
    "alias":"oppo-reno5-5g",
    "rating":2.6884003174784388,
    "content":"Lorem ipsum dolor sit amet, consectetuer adipiscing elit. Aenean commodo ligula eget dolor. Aenean massa. Cum sociis natoque penatibus et magnis dis parturient montes, nascetur ridiculus mus. Donec quam felis, ultricies nec, pellentesque eu, pretium quis, sem. Nulla consequat massa quis enim. Donec pede justo, fringilla vel, aliquet nec, vulputate eget, arcu. In enim justo, rhoncus ut, imperdiet a, venenatis vitae, justo. Nullam dictum felis eu pede mollis pretium. Integer tincidunt. Cras dapibus. Vivamus elementum semper nisi. Aenean vulputate eleifend tellus. Aenean leo ligula, porttitor eu, consequat vitae, eleifend ac, enim. Aliquam lorem ante, dapibus in, viverra quis, feugiat a, tellus. Phasellus viverra nulla ut metus varius laoreet. Quisque rutrum. Aenean imperdiet. Etiam ultricies nisi vel augue. Curabitur ullamcorper ultricies nisi. Nam eget dui. Etiam rhoncus. Maecenas tempus, tellus eget condimentum rhoncus, sem quam semper libero, sit amet adipiscing sem neque sed ipsum. Nam quam nunc, blandit vel, luctus pulvinar, hendrerit id, lorem. Maecenas nec odio et ante tincidunt tempus. Donec vitae sapien ut libero venenatis faucibus. Nullam quis ante. Etiam sit amet orci eget eros faucibus tincidunt. Duis leo. Sed fringilla mauris sit amet nibh. Donec sodales sagittis magna. Sed consequat, leo eget bibendum sodales, augue velit cursus nunc,",
    "versions":[
      {
        "id":0,
        "title":"3GB-32GB",
        "alias":"3gb-32gb",
        "image":"/upload/OPPO Reno5 5G.png" ,
        "price":103.43 ,
        "salePrice":49.83
      },{
        "id":1,
        "title":"4GB-64GB",
        "alias":"4gb-64gb",
        "image":"/upload/OPPO Reno5 5G.png" ,
        "price":124.12
      }
    ],
      "albums":[
        {
          "image":"/upload/OPPO Reno5 5G.png"
        },
        {
          "image":"/upload/OPPO Reno5 5G.png"
        },
        {
          "image":"/upload/OPPO Reno5 5G.png"
        },
        {
          "image":"/upload/OPPO Reno5 5G.png"
        },
        {
          "image":"/upload/OPPO Reno5 5G.png"
        }
      ]
  }
,{
    "id":32,
    "title":"OPPO Reno6 5G",
    "alias":"oppo-reno6-5g",
    "rating":4.314501979500599,
    "content":"Lorem ipsum dolor sit amet, consectetuer adipiscing elit. Aenean commodo ligula eget dolor. Aenean massa. Cum sociis natoque penatibus et magnis dis parturient montes, nascetur ridiculus mus. Donec quam felis, ultricies nec, pellentesque eu, pretium quis, sem. Nulla consequat massa quis enim. Donec pede justo, fringilla vel, aliquet nec, vulputate eget, arcu. In enim justo, rhoncus ut, imperdiet a, venenatis vitae, justo. Nullam dictum felis eu pede mollis pretium. Integer tincidunt. Cras dapibus. Vivamus elementum semper nisi. Aenean vulputate eleifend tellus. Aenean leo ligula, porttitor eu, consequat vitae, eleifend ac, enim. Aliquam lorem ante, dapibus in, viverra quis, feugiat a, tellus. Phasellus viverra nulla ut metus varius laoreet. Quisque rutrum. Aenean imperdiet. Etiam ultricies nisi vel augue. Curabitur ullamcorper ultricies nisi. Nam eget dui. Etiam rhoncus. Maecenas tempus, tellus eget condimentum rhoncus, sem quam semper libero, sit amet adipiscing sem neque sed ipsum. Nam quam nunc, blandit vel, luctus pulvinar, hendrerit id, lorem. Maecenas nec odio et ante tincidunt tempus. Donec vitae sapien ut libero venenatis faucibus. Nullam quis ante. Etiam sit amet orci eget eros faucibus tincidunt. Duis leo. Sed fringilla mauris sit amet nibh. Donec sodales sagittis magna. Sed consequat, leo eget bibendum sodales, augue velit cursus nunc,",
    "versions":[
      {
        "id":0,
        "title":"3GB-32GB",
        "alias":"3gb-32gb",
        "image":"/upload/OPPO Reno6 5G.png" ,
        "price":396.41 ,
        "salePrice":119.61
      },{
        "id":1,
        "title":"4GB-64GB",
        "alias":"4gb-64gb",
        "image":"/upload/OPPO Reno6 5G.png" ,
        "price":475.69
      }
    ],
      "albums":[
        {
          "image":"/upload/OPPO Reno6 5G.png"
        },
        {
          "image":"/upload/OPPO Reno6 5G.png"
        },
        {
          "image":"/upload/OPPO Reno6 5G.png"
        },
        {
          "image":"/upload/OPPO Reno6 5G.png"
        },
        {
          "image":"/upload/OPPO Reno6 5G.png"
        }
      ]
  }
,{
    "id":33,
    "title":"Samsung Galaxy A22",
    "alias":"samsung-galaxy-a22",
    "rating":1.4431602794057385,
    "content":"Lorem ipsum dolor sit amet, consectetuer adipiscing elit. Aenean commodo ligula eget dolor. Aenean massa. Cum sociis natoque penatibus et magnis dis parturient montes, nascetur ridiculus mus. Donec quam felis, ultricies nec, pellentesque eu, pretium quis, sem. Nulla consequat massa quis enim. Donec pede justo, fringilla vel, aliquet nec, vulputate eget, arcu. In enim justo, rhoncus ut, imperdiet a, venenatis vitae, justo. Nullam dictum felis eu pede mollis pretium. Integer tincidunt. Cras dapibus. Vivamus elementum semper nisi. Aenean vulputate eleifend tellus. Aenean leo ligula, porttitor eu, consequat vitae, eleifend ac, enim. Aliquam lorem ante, dapibus in, viverra quis, feugiat a, tellus. Phasellus viverra nulla ut metus varius laoreet. Quisque rutrum. Aenean imperdiet. Etiam ultricies nisi vel augue. Curabitur ullamcorper ultricies nisi. Nam eget dui. Etiam rhoncus. Maecenas tempus, tellus eget condimentum rhoncus, sem quam semper libero, sit amet adipiscing sem neque sed ipsum. Nam quam nunc, blandit vel, luctus pulvinar, hendrerit id, lorem. Maecenas nec odio et ante tincidunt tempus. Donec vitae sapien ut libero venenatis faucibus. Nullam quis ante. Etiam sit amet orci eget eros faucibus tincidunt. Duis leo. Sed fringilla mauris sit amet nibh. Donec sodales sagittis magna. Sed consequat, leo eget bibendum sodales, augue velit cursus nunc,",
    "versions":[
      {
        "id":0,
        "title":"3GB-32GB",
        "alias":"3gb-32gb",
        "image":"/upload/Samsung Galaxy A22.png" ,
        "price":311.25
      },{
        "id":1,
        "title":"4GB-64GB",
        "alias":"4gb-64gb",
        "image":"/upload/Samsung Galaxy A22.png" ,
        "price":373.50
      }
    ],
      "albums":[
        {
          "image":"/upload/Samsung Galaxy A22.png"
        },
        {
          "image":"/upload/Samsung Galaxy A22.png"
        },
        {
          "image":"/upload/Samsung Galaxy A22.png"
        },
        {
          "image":"/upload/Samsung Galaxy A22.png"
        },
        {
          "image":"/upload/Samsung Galaxy A22.png"
        }
      ]
  }
,{
    "id":34,
    "title":"Samsung Galaxy M51",
    "alias":"samsung-galaxy-m51",
    "rating":3.103706213561115,
    "content":"Lorem ipsum dolor sit amet, consectetuer adipiscing elit. Aenean commodo ligula eget dolor. Aenean massa. Cum sociis natoque penatibus et magnis dis parturient montes, nascetur ridiculus mus. Donec quam felis, ultricies nec, pellentesque eu, pretium quis, sem. Nulla consequat massa quis enim. Donec pede justo, fringilla vel, aliquet nec, vulputate eget, arcu. In enim justo, rhoncus ut, imperdiet a, venenatis vitae, justo. Nullam dictum felis eu pede mollis pretium. Integer tincidunt. Cras dapibus. Vivamus elementum semper nisi. Aenean vulputate eleifend tellus. Aenean leo ligula, porttitor eu, consequat vitae, eleifend ac, enim. Aliquam lorem ante, dapibus in, viverra quis, feugiat a, tellus. Phasellus viverra nulla ut metus varius laoreet. Quisque rutrum. Aenean imperdiet. Etiam ultricies nisi vel augue. Curabitur ullamcorper ultricies nisi. Nam eget dui. Etiam rhoncus. Maecenas tempus, tellus eget condimentum rhoncus, sem quam semper libero, sit amet adipiscing sem neque sed ipsum. Nam quam nunc, blandit vel, luctus pulvinar, hendrerit id, lorem. Maecenas nec odio et ante tincidunt tempus. Donec vitae sapien ut libero venenatis faucibus. Nullam quis ante. Etiam sit amet orci eget eros faucibus tincidunt. Duis leo. Sed fringilla mauris sit amet nibh. Donec sodales sagittis magna. Sed consequat, leo eget bibendum sodales, augue velit cursus nunc,",
    "versions":[
      {
        "id":0,
        "title":"3GB-32GB",
        "alias":"3gb-32gb",
        "image":"/upload/Samsung Galaxy M51.png"
      },{
        "id":1,
        "title":"4GB-64GB",
        "alias":"4gb-64gb",
        "image":"/upload/Samsung Galaxy M51.png"
      }
    ],
      "albums":[
        {
          "image":"/upload/Samsung Galaxy M51.png"
        },
        {
          "image":"/upload/Samsung Galaxy M51.png"
        },
        {
          "image":"/upload/Samsung Galaxy M51.png"
        },
        {
          "image":"/upload/Samsung Galaxy M51.png"
        },
        {
          "image":"/upload/Samsung Galaxy M51.png"
        }
      ]
  }
,{
    "id":35,
    "title":"Vivo Y21s",
    "alias":"vivo-y21s",
    "rating":4.296435166328774,
    "content":"Lorem ipsum dolor sit amet, consectetuer adipiscing elit. Aenean commodo ligula eget dolor. Aenean massa. Cum sociis natoque penatibus et magnis dis parturient montes, nascetur ridiculus mus. Donec quam felis, ultricies nec, pellentesque eu, pretium quis, sem. Nulla consequat massa quis enim. Donec pede justo, fringilla vel, aliquet nec, vulputate eget, arcu. In enim justo, rhoncus ut, imperdiet a, venenatis vitae, justo. Nullam dictum felis eu pede mollis pretium. Integer tincidunt. Cras dapibus. Vivamus elementum semper nisi. Aenean vulputate eleifend tellus. Aenean leo ligula, porttitor eu, consequat vitae, eleifend ac, enim. Aliquam lorem ante, dapibus in, viverra quis, feugiat a, tellus. Phasellus viverra nulla ut metus varius laoreet. Quisque rutrum. Aenean imperdiet. Etiam ultricies nisi vel augue. Curabitur ullamcorper ultricies nisi. Nam eget dui. Etiam rhoncus. Maecenas tempus, tellus eget condimentum rhoncus, sem quam semper libero, sit amet adipiscing sem neque sed ipsum. Nam quam nunc, blandit vel, luctus pulvinar, hendrerit id, lorem. Maecenas nec odio et ante tincidunt tempus. Donec vitae sapien ut libero venenatis faucibus. Nullam quis ante. Etiam sit amet orci eget eros faucibus tincidunt. Duis leo. Sed fringilla mauris sit amet nibh. Donec sodales sagittis magna. Sed consequat, leo eget bibendum sodales, augue velit cursus nunc,",
    "versions":[
      {
        "id":0,
        "title":"3GB-32GB",
        "alias":"3gb-32gb",
        "image":"/upload/Vivo Y21s.png" ,
        "price":125.79
      },{
        "id":1,
        "title":"4GB-64GB",
        "alias":"4gb-64gb",
        "image":"/upload/Vivo Y21s.png" ,
        "price":150.95
      }
    ],
      "albums":[
        {
          "image":"/upload/Vivo Y21s.png"
        },
        {
          "image":"/upload/Vivo Y21s.png"
        },
        {
          "image":"/upload/Vivo Y21s.png"
        },
        {
          "image":"/upload/Vivo Y21s.png"
        },
        {
          "image":"/upload/Vivo Y21s.png"
        }
      ]
  }
,{
    "id":36,
    "title":"Vsmart Aris",
    "alias":"vsmart-aris",
    "rating":4.604421809608819,
    "content":"Lorem ipsum dolor sit amet, consectetuer adipiscing elit. Aenean commodo ligula eget dolor. Aenean massa. Cum sociis natoque penatibus et magnis dis parturient montes, nascetur ridiculus mus. Donec quam felis, ultricies nec, pellentesque eu, pretium quis, sem. Nulla consequat massa quis enim. Donec pede justo, fringilla vel, aliquet nec, vulputate eget, arcu. In enim justo, rhoncus ut, imperdiet a, venenatis vitae, justo. Nullam dictum felis eu pede mollis pretium. Integer tincidunt. Cras dapibus. Vivamus elementum semper nisi. Aenean vulputate eleifend tellus. Aenean leo ligula, porttitor eu, consequat vitae, eleifend ac, enim. Aliquam lorem ante, dapibus in, viverra quis, feugiat a, tellus. Phasellus viverra nulla ut metus varius laoreet. Quisque rutrum. Aenean imperdiet. Etiam ultricies nisi vel augue. Curabitur ullamcorper ultricies nisi. Nam eget dui. Etiam rhoncus. Maecenas tempus, tellus eget condimentum rhoncus, sem quam semper libero, sit amet adipiscing sem neque sed ipsum. Nam quam nunc, blandit vel, luctus pulvinar, hendrerit id, lorem. Maecenas nec odio et ante tincidunt tempus. Donec vitae sapien ut libero venenatis faucibus. Nullam quis ante. Etiam sit amet orci eget eros faucibus tincidunt. Duis leo. Sed fringilla mauris sit amet nibh. Donec sodales sagittis magna. Sed consequat, leo eget bibendum sodales, augue velit cursus nunc,",
    "versions":[
      {
        "id":0,
        "title":"3GB-32GB",
        "alias":"3gb-32gb",
        "image":"/upload/Vsmart Aris.png" ,
        "price":368.16
      },{
        "id":1,
        "title":"4GB-64GB",
        "alias":"4gb-64gb",
        "image":"/upload/Vsmart Aris.png" ,
        "price":441.79
      }
    ],
      "albums":[
        {
          "image":"/upload/Vsmart Aris.png"
        },
        {
          "image":"/upload/Vsmart Aris.png"
        },
        {
          "image":"/upload/Vsmart Aris.png"
        },
        {
          "image":"/upload/Vsmart Aris.png"
        },
        {
          "image":"/upload/Vsmart Aris.png"
        }
      ]
  }
,{
    "id":37,
    "title":"Vsmart Star 5",
    "alias":"vsmart-star-5",
    "rating":3.309941900904181,
    "content":"Lorem ipsum dolor sit amet, consectetuer adipiscing elit. Aenean commodo ligula eget dolor. Aenean massa. Cum sociis natoque penatibus et magnis dis parturient montes, nascetur ridiculus mus. Donec quam felis, ultricies nec, pellentesque eu, pretium quis, sem. Nulla consequat massa quis enim. Donec pede justo, fringilla vel, aliquet nec, vulputate eget, arcu. In enim justo, rhoncus ut, imperdiet a, venenatis vitae, justo. Nullam dictum felis eu pede mollis pretium. Integer tincidunt. Cras dapibus. Vivamus elementum semper nisi. Aenean vulputate eleifend tellus. Aenean leo ligula, porttitor eu, consequat vitae, eleifend ac, enim. Aliquam lorem ante, dapibus in, viverra quis, feugiat a, tellus. Phasellus viverra nulla ut metus varius laoreet. Quisque rutrum. Aenean imperdiet. Etiam ultricies nisi vel augue. Curabitur ullamcorper ultricies nisi. Nam eget dui. Etiam rhoncus. Maecenas tempus, tellus eget condimentum rhoncus, sem quam semper libero, sit amet adipiscing sem neque sed ipsum. Nam quam nunc, blandit vel, luctus pulvinar, hendrerit id, lorem. Maecenas nec odio et ante tincidunt tempus. Donec vitae sapien ut libero venenatis faucibus. Nullam quis ante. Etiam sit amet orci eget eros faucibus tincidunt. Duis leo. Sed fringilla mauris sit amet nibh. Donec sodales sagittis magna. Sed consequat, leo eget bibendum sodales, augue velit cursus nunc,",
    "versions":[
      {
        "id":0,
        "title":"3GB-32GB",
        "alias":"3gb-32gb",
        "image":"/upload/Vsmart Star 5.png"
      },{
        "id":1,
        "title":"4GB-64GB",
        "alias":"4gb-64gb",
        "image":"/upload/Vsmart Star 5.png"
      }
    ],
      "albums":[
        {
          "image":"/upload/Vsmart Star 5.png"
        },
        {
          "image":"/upload/Vsmart Star 5.png"
        },
        {
          "image":"/upload/Vsmart Star 5.png"
        },
        {
          "image":"/upload/Vsmart Star 5.png"
        },
        {
          "image":"/upload/Vsmart Star 5.png"
        }
      ]
  }
,{
    "id":38,
    "title":"Xiaomi 11 Lite 5G",
    "alias":"xiaomi-11-lite-5g",
    "rating":2.031863821787656,
    "content":"Lorem ipsum dolor sit amet, consectetuer adipiscing elit. Aenean commodo ligula eget dolor. Aenean massa. Cum sociis natoque penatibus et magnis dis parturient montes, nascetur ridiculus mus. Donec quam felis, ultricies nec, pellentesque eu, pretium quis, sem. Nulla consequat massa quis enim. Donec pede justo, fringilla vel, aliquet nec, vulputate eget, arcu. In enim justo, rhoncus ut, imperdiet a, venenatis vitae, justo. Nullam dictum felis eu pede mollis pretium. Integer tincidunt. Cras dapibus. Vivamus elementum semper nisi. Aenean vulputate eleifend tellus. Aenean leo ligula, porttitor eu, consequat vitae, eleifend ac, enim. Aliquam lorem ante, dapibus in, viverra quis, feugiat a, tellus. Phasellus viverra nulla ut metus varius laoreet. Quisque rutrum. Aenean imperdiet. Etiam ultricies nisi vel augue. Curabitur ullamcorper ultricies nisi. Nam eget dui. Etiam rhoncus. Maecenas tempus, tellus eget condimentum rhoncus, sem quam semper libero, sit amet adipiscing sem neque sed ipsum. Nam quam nunc, blandit vel, luctus pulvinar, hendrerit id, lorem. Maecenas nec odio et ante tincidunt tempus. Donec vitae sapien ut libero venenatis faucibus. Nullam quis ante. Etiam sit amet orci eget eros faucibus tincidunt. Duis leo. Sed fringilla mauris sit amet nibh. Donec sodales sagittis magna. Sed consequat, leo eget bibendum sodales, augue velit cursus nunc,",
    "versions":[
      {
        "id":0,
        "title":"3GB-32GB",
        "alias":"3gb-32gb",
        "image":"/upload/Xiaomi 11 Lite 5G.png" ,
        "price":93.28
      },{
        "id":1,
        "title":"4GB-64GB",
        "alias":"4gb-64gb",
        "image":"/upload/Xiaomi 11 Lite 5G.png" ,
        "price":111.94 ,
        "salePrice":50.93
      }
    ],
      "albums":[
        {
          "image":"/upload/Xiaomi 11 Lite 5G.png"
        },
        {
          "image":"/upload/Xiaomi 11 Lite 5G.png"
        },
        {
          "image":"/upload/Xiaomi 11 Lite 5G.png"
        },
        {
          "image":"/upload/Xiaomi 11 Lite 5G.png"
        },
        {
          "image":"/upload/Xiaomi 11 Lite 5G.png"
        }
      ]
  }
,{
    "id":39,
    "title":"Xiaomi Redmi 9T",
    "alias":"xiaomi-redmi-9t",
    "rating":2.9735875241394294,
    "content":"Lorem ipsum dolor sit amet, consectetuer adipiscing elit. Aenean commodo ligula eget dolor. Aenean massa. Cum sociis natoque penatibus et magnis dis parturient montes, nascetur ridiculus mus. Donec quam felis, ultricies nec, pellentesque eu, pretium quis, sem. Nulla consequat massa quis enim. Donec pede justo, fringilla vel, aliquet nec, vulputate eget, arcu. In enim justo, rhoncus ut, imperdiet a, venenatis vitae, justo. Nullam dictum felis eu pede mollis pretium. Integer tincidunt. Cras dapibus. Vivamus elementum semper nisi. Aenean vulputate eleifend tellus. Aenean leo ligula, porttitor eu, consequat vitae, eleifend ac, enim. Aliquam lorem ante, dapibus in, viverra quis, feugiat a, tellus. Phasellus viverra nulla ut metus varius laoreet. Quisque rutrum. Aenean imperdiet. Etiam ultricies nisi vel augue. Curabitur ullamcorper ultricies nisi. Nam eget dui. Etiam rhoncus. Maecenas tempus, tellus eget condimentum rhoncus, sem quam semper libero, sit amet adipiscing sem neque sed ipsum. Nam quam nunc, blandit vel, luctus pulvinar, hendrerit id, lorem. Maecenas nec odio et ante tincidunt tempus. Donec vitae sapien ut libero venenatis faucibus. Nullam quis ante. Etiam sit amet orci eget eros faucibus tincidunt. Duis leo. Sed fringilla mauris sit amet nibh. Donec sodales sagittis magna. Sed consequat, leo eget bibendum sodales, augue velit cursus nunc,",
    "versions":[
      {
        "id":0,
        "title":"3GB-32GB",
        "alias":"3gb-32gb",
        "image":"/upload/Xiaomi Redmi 9T.png"
      },{
        "id":1,
        "title":"4GB-64GB",
        "alias":"4gb-64gb",
        "image":"/upload/Xiaomi Redmi 9T.png"
      }
    ],
      "albums":[
        {
          "image":"/upload/Xiaomi Redmi 9T.png"
        },
        {
          "image":"/upload/Xiaomi Redmi 9T.png"
        },
        {
          "image":"/upload/Xiaomi Redmi 9T.png"
        },
        {
          "image":"/upload/Xiaomi Redmi 9T.png"
        },
        {
          "image":"/upload/Xiaomi Redmi 9T.png"
        }
      ]
  }
,{
    "id":40,
    "title":"Xiaomi Redmi 10",
    "alias":"xiaomi-redmi-10",
    "rating":1.8631379384791646,
    "content":"Lorem ipsum dolor sit amet, consectetuer adipiscing elit. Aenean commodo ligula eget dolor. Aenean massa. Cum sociis natoque penatibus et magnis dis parturient montes, nascetur ridiculus mus. Donec quam felis, ultricies nec, pellentesque eu, pretium quis, sem. Nulla consequat massa quis enim. Donec pede justo, fringilla vel, aliquet nec, vulputate eget, arcu. In enim justo, rhoncus ut, imperdiet a, venenatis vitae, justo. Nullam dictum felis eu pede mollis pretium. Integer tincidunt. Cras dapibus. Vivamus elementum semper nisi. Aenean vulputate eleifend tellus. Aenean leo ligula, porttitor eu, consequat vitae, eleifend ac, enim. Aliquam lorem ante, dapibus in, viverra quis, feugiat a, tellus. Phasellus viverra nulla ut metus varius laoreet. Quisque rutrum. Aenean imperdiet. Etiam ultricies nisi vel augue. Curabitur ullamcorper ultricies nisi. Nam eget dui. Etiam rhoncus. Maecenas tempus, tellus eget condimentum rhoncus, sem quam semper libero, sit amet adipiscing sem neque sed ipsum. Nam quam nunc, blandit vel, luctus pulvinar, hendrerit id, lorem. Maecenas nec odio et ante tincidunt tempus. Donec vitae sapien ut libero venenatis faucibus. Nullam quis ante. Etiam sit amet orci eget eros faucibus tincidunt. Duis leo. Sed fringilla mauris sit amet nibh. Donec sodales sagittis magna. Sed consequat, leo eget bibendum sodales, augue velit cursus nunc,",
    "versions":[
      {
        "id":0,
        "title":"3GB-32GB",
        "alias":"3gb-32gb",
        "image":"/upload/Xiaomi Redmi 10.png" ,
        "price":359.39
      },{
        "id":1,
        "title":"4GB-64GB",
        "alias":"4gb-64gb",
        "image":"/upload/Xiaomi Redmi 10.png" ,
        "price":431.27
      }
    ],
      "albums":[
        {
          "image":"/upload/Xiaomi Redmi 10.png"
        },
        {
          "image":"/upload/Xiaomi Redmi 10.png"
        },
        {
          "image":"/upload/Xiaomi Redmi 10.png"
        },
        {
          "image":"/upload/Xiaomi Redmi 10.png"
        },
        {
          "image":"/upload/Xiaomi Redmi 10.png"
        }
      ]
  }
,{
    "id":41,
    "title":"Xiaomi Redmi Note 10",
    "alias":"xiaomi-redmi-note-10",
    "rating":1.363637650767452,
    "content":"Lorem ipsum dolor sit amet, consectetuer adipiscing elit. Aenean commodo ligula eget dolor. Aenean massa. Cum sociis natoque penatibus et magnis dis parturient montes, nascetur ridiculus mus. Donec quam felis, ultricies nec, pellentesque eu, pretium quis, sem. Nulla consequat massa quis enim. Donec pede justo, fringilla vel, aliquet nec, vulputate eget, arcu. In enim justo, rhoncus ut, imperdiet a, venenatis vitae, justo. Nullam dictum felis eu pede mollis pretium. Integer tincidunt. Cras dapibus. Vivamus elementum semper nisi. Aenean vulputate eleifend tellus. Aenean leo ligula, porttitor eu, consequat vitae, eleifend ac, enim. Aliquam lorem ante, dapibus in, viverra quis, feugiat a, tellus. Phasellus viverra nulla ut metus varius laoreet. Quisque rutrum. Aenean imperdiet. Etiam ultricies nisi vel augue. Curabitur ullamcorper ultricies nisi. Nam eget dui. Etiam rhoncus. Maecenas tempus, tellus eget condimentum rhoncus, sem quam semper libero, sit amet adipiscing sem neque sed ipsum. Nam quam nunc, blandit vel, luctus pulvinar, hendrerit id, lorem. Maecenas nec odio et ante tincidunt tempus. Donec vitae sapien ut libero venenatis faucibus. Nullam quis ante. Etiam sit amet orci eget eros faucibus tincidunt. Duis leo. Sed fringilla mauris sit amet nibh. Donec sodales sagittis magna. Sed consequat, leo eget bibendum sodales, augue velit cursus nunc,",
    "versions":[
      {
        "id":0,
        "title":"3GB-32GB",
        "alias":"3gb-32gb",
        "image":"/upload/Xiaomi Redmi Note 10.png" ,
        "price":276.65
      },{
        "id":1,
        "title":"4GB-64GB",
        "alias":"4gb-64gb",
        "image":"/upload/Xiaomi Redmi Note 10.png" ,
        "price":331.98 ,
        "salePrice":155.45
      }
    ],
      "albums":[
        {
          "image":"/upload/Xiaomi Redmi Note 10.png"
        },
        {
          "image":"/upload/Xiaomi Redmi Note 10.png"
        },
        {
          "image":"/upload/Xiaomi Redmi Note 10.png"
        },
        {
          "image":"/upload/Xiaomi Redmi Note 10.png"
        },
        {
          "image":"/upload/Xiaomi Redmi Note 10.png"
        }
      ]
  }
]